[{"op": "add", "path": "/channels/0/samples/9", "value": {"data": [0.48643234372138977], "modifiers": [{"data": null, "name": "lumi", "type": "lumi"}, {"data": [0.48643234143013536], "name": "staterror_WREM_cuts", "type": "staterror"}, {"data": {"hi_data": [0.48643234372138977], "lo_data": [0.48643234372138977]}, "name": "EG_Eff", "type": "histosys"}, {"data": {"hi_data": [0.48643234372138977], "lo_data": [0.48643234372138977]}, "name": "EG_Iso", "type": "histosys"}, {"data": {"hi_data": [0.48643234372138977], "lo_data": [0.48643234372138977]}, "name": "EG_Reco", "type": "histosys"}, {"data": {"hi_data": [0.48643234372138977], "lo_data": [0.48643234372138977]}, "name": "JVT", "type": "histosys"}, {"data": {"hi_data": [0.48643234372138977], "lo_data": [0.48643234372138977]}, "name": "MUON_Eff_BadMuon_stat", "type": "histosys"}, {"data": {"hi_data": [0.48643234372138977], "lo_data": [0.48643234372138977]}, "name": "MUON_Eff_BadMuon_sys", "type": "histosys"}, {"data": {"hi_data": [0.48643234372138977], "lo_data": [0.48643234372138977]}, "name": "MUON_Eff_Iso_stat", "type": "histosys"}, {"data": {"hi_data": [0.48643234372138977], "lo_data": [0.48643234372138977]}, "name": "MUON_Eff_Iso_sys", "type": "histosys"}, {"data": {"hi_data": [0.48643234372138977], "lo_data": [0.48643234372138977]}, "name": "MUON_Eff_stat", "type": "histosys"}, {"data": {"hi_data": [0.48643234372138977], "lo_data": [0.48643234372138977]}, "name": "MUON_Eff_stat_lowpt", "type": "histosys"}, {"data": {"hi_data": [0.48643234372138977], "lo_data": [0.48643234372138977]}, "name": "MUON_Eff_sys", "type": "histosys"}, {"data": {"hi_data": [0.48643234372138977], "lo_data": [0.48643234372138977]}, "name": "MUON_Eff_sys_lowpt", "type": "histosys"}, {"data": {"hi_data": [0.48643234372138977], "lo_data": [0.48643234372138977]}, "name": "MUON_TTVA_stat", "type": "histosys"}, {"data": {"hi_data": [0.48643234372138977], "lo_data": [0.48643234372138977]}, "name": "MUON_TTVA_sys", "type": "histosys"}, {"data": {"hi_data": [0.48643234372138977], "lo_data": [0.48643234372138977]}, "name": "btag_BT", "type": "histosys"}, {"data": {"hi_data": [0.48643234372138977], "lo_data": [0.48643234372138977]}, "name": "btag_CT", "type": "histosys"}, {"data": {"hi_data": [0.48643234372138977], "lo_data": [0.48643234372138977]}, "name": "btag_Extra", "type": "histosys"}, {"data": {"hi_data": [0.48643234372138977], "lo_data": [0.48643234372138977]}, "name": "btag_ExtraFromCharm", "type": "histosys"}, {"data": {"hi_data": [0.48643234372138977], "lo_data": [0.48643234372138977]}, "name": "btag_LightT", "type": "histosys"}, {"data": {"hi_data": [0.48643234372138977], "lo_data": [0.48643234372138977]}, "name": "pileup", "type": "histosys"}, {"data": {"hi_data": [0.48643234372138977], "lo_data": [0.48643234372138977]}, "name": "EG_RESOLUTION_ALL", "type": "histosys"}, {"data": {"hi_data": [0.48643234372138977], "lo_data": [0.48643234372138977]}, "name": "EG_SCALE_AF2", "type": "histosys"}, {"data": {"hi_data": [0.48643234372138977], "lo_data": [0.48643234372138977]}, "name": "EG_SCALE_ALL", "type": "histosys"}, {"data": {"hi_data": [0.48643234372138977], "lo_data": [0.48643234372138977]}, "name": "JER_DataVsMC", "type": "histosys"}, {"data": {"hi_data": [0.48643234372138977], "lo_data": [0.48643234372138977]}, "name": "JER_EffectiveNP_1", "type": "histosys"}, {"data": {"hi_data": [0.48643234372138977], "lo_data": [0.48643234372138977]}, "name": "JER_EffectiveNP_10", "type": "histosys"}, {"data": {"hi_data": [0.48643234372138977], "lo_data": [0.48643234372138977]}, "name": "JER_EffectiveNP_11", "type": "histosys"}, {"data": {"hi_data": [0.48643234372138977], "lo_data": [0.48643234372138977]}, "name": "JER_EffectiveNP_12restTerm", "type": "histosys"}, {"data": {"hi_data": [0.48643234372138977], "lo_data": [0.48643234372138977]}, "name": "JER_EffectiveNP_2", "type": "histosys"}, {"data": {"hi_data": [0.48643234372138977], "lo_data": [0.48643234372138977]}, "name": "JER_EffectiveNP_3", "type": "histosys"}, {"data": {"hi_data": [0.48643234372138977], "lo_data": [0.48643234372138977]}, "name": "JER_EffectiveNP_4", "type": "histosys"}, {"data": {"hi_data": [0.48643234372138977], "lo_data": [0.48643234372138977]}, "name": "JER_EffectiveNP_5", "type": "histosys"}, {"data": {"hi_data": [0.48643234372138977], "lo_data": [0.48643234372138977]}, "name": "JER_EffectiveNP_6", "type": "histosys"}, {"data": {"hi_data": [0.48643234372138977], "lo_data": [0.48643234372138977]}, "name": "JER_EffectiveNP_7", "type": "histosys"}, {"data": {"hi_data": [0.48643234372138977], "lo_data": [0.48643234372138977]}, "name": "JER_EffectiveNP_8", "type": "histosys"}, {"data": {"hi_data": [0.48643234372138977], "lo_data": [0.48643234372138977]}, "name": "JER_EffectiveNP_9", "type": "histosys"}, {"data": {"hi_data": [0.48643234372138977], "lo_data": [0.48643234372138977]}, "name": "JES_BJES_Response", "type": "histosys"}, {"data": {"hi_data": [0.48643234372138977], "lo_data": [0.48643234372138977]}, "name": "JES_Comb_Baseline_Kin", "type": "histosys"}, {"data": {"hi_data": [0.48643234372138977], "lo_data": [0.48643234372138977]}, "name": "JES_Comb_Modelling_Kin", "type": "histosys"}, {"data": {"hi_data": [0.48643234372138977], "lo_data": [0.48643234372138977]}, "name": "JES_Comb_TotalStat_Kin", "type": "histosys"}, {"data": {"hi_data": [0.48643234372138977], "lo_data": [0.48643234372138977]}, "name": "JES_Comb_Tracking_Kin", "type": "histosys"}, {"data": {"hi_data": [0.48643234372138977], "lo_data": [0.48643234372138977]}, "name": "JES_EffectiveNP_Detector1", "type": "histosys"}, {"data": {"hi_data": [0.48643234372138977], "lo_data": [0.48643234372138977]}, "name": "JES_EffectiveNP_Detector2", "type": "histosys"}, {"data": {"hi_data": [0.48643234372138977], "lo_data": [0.48643234372138977]}, "name": "JES_EffectiveNP_Mixed1", "type": "histosys"}, {"data": {"hi_data": [0.48643234372138977], "lo_data": [0.48643234372138977]}, "name": "JES_EffectiveNP_Mixed2", "type": "histosys"}, {"data": {"hi_data": [0.48643234372138977], "lo_data": [0.48643234372138977]}, "name": "JES_EffectiveNP_Mixed3", "type": "histosys"}, {"data": {"hi_data": [0.48643234372138977], "lo_data": [0.48643234372138977]}, "name": "JES_EffectiveNP_Modelling1", "type": "histosys"}, {"data": {"hi_data": [0.48643234372138977], "lo_data": [0.48643234372138977]}, "name": "JES_EffectiveNP_Modelling2", "type": "histosys"}, {"data": {"hi_data": [0.48643234372138977], "lo_data": [0.48643234372138977]}, "name": "JES_EffectiveNP_Modelling3", "type": "histosys"}, {"data": {"hi_data": [0.48643234372138977], "lo_data": [0.48643234372138977]}, "name": "JES_EffectiveNP_Modelling4", "type": "histosys"}, {"data": {"hi_data": [0.48643234372138977], "lo_data": [0.48643234372138977]}, "name": "JES_EffectiveNP_Statistical1", "type": "histosys"}, {"data": {"hi_data": [0.48643234372138977], "lo_data": [0.48643234372138977]}, "name": "JES_EffectiveNP_Statistical2", "type": "histosys"}, {"data": {"hi_data": [0.48643234372138977], "lo_data": [0.48643234372138977]}, "name": "JES_EffectiveNP_Statistical3", "type": "histosys"}, {"data": {"hi_data": [0.48643234372138977], "lo_data": [0.48643234372138977]}, "name": "JES_EffectiveNP_Statistical4", "type": "histosys"}, {"data": {"hi_data": [0.48643234372138977], "lo_data": [0.48643234372138977]}, "name": "JES_EffectiveNP_Statistical5", "type": "histosys"}, {"data": {"hi_data": [0.48643234372138977], "lo_data": [0.48643234372138977]}, "name": "JES_EffectiveNP_Statistical6", "type": "histosys"}, {"data": {"hi_data": [0.48643234372138977], "lo_data": [0.48643234372138977]}, "name": "JES_EtaIntercalibration_Modelling", "type": "histosys"}, {"data": {"hi_data": [0.48643234372138977], "lo_data": [0.48643234372138977]}, "name": "JES_EtaIntercalibration_NonClosure_highE", "type": "histosys"}, {"data": {"hi_data": [0.48643234372138977], "lo_data": [0.48643234372138977]}, "name": "JES_EtaIntercalibration_NonClosure_negEta", "type": "histosys"}, {"data": {"hi_data": [0.48643234372138977], "lo_data": [0.48643234372138977]}, "name": "JES_EtaIntercalibration_NonClosure_posEta", "type": "histosys"}, {"data": {"hi_data": [0.48643234372138977], "lo_data": [0.48643234372138977]}, "name": "JES_EtaIntercalibration_TotalStat", "type": "histosys"}, {"data": {"hi_data": [0.48643234372138977], "lo_data": [0.48643234372138977]}, "name": "JES_Flavor_Composition", "type": "histosys"}, {"data": {"hi_data": [0.48643234372138977], "lo_data": [0.48643234372138977]}, "name": "JES_Flavor_Response", "type": "histosys"}, {"data": {"hi_data": [0.48643234372138977], "lo_data": [0.48643234372138977]}, "name": "JES_Pileup_OffsetMu", "type": "histosys"}, {"data": {"hi_data": [0.48643234372138977], "lo_data": [0.48643234372138977]}, "name": "JES_Pileup_OffsetNPV", "type": "histosys"}, {"data": {"hi_data": [0.48643234372138977], "lo_data": [0.48643234372138977]}, "name": "JES_Pileup_PtTerm", "type": "histosys"}, {"data": {"hi_data": [0.48643234372138977], "lo_data": [0.48643234372138977]}, "name": "JES_Pileup_RhoTopology", "type": "histosys"}, {"data": {"hi_data": [0.48643234372138977], "lo_data": [0.48643234372138977]}, "name": "JES_SingleParticle_HighPt", "type": "histosys"}, {"data": {"hi_data": [0.48643234372138977], "lo_data": [0.48643234372138977]}, "name": "MET_SoftTrk", "type": "histosys"}, {"data": {"hi_data": [0.48643234372138977], "lo_data": [0.48643234372138977]}, "name": "MET_SoftTrk_ResoPara", "type": "histosys"}, {"data": {"hi_data": [0.48643234372138977], "lo_data": [0.48643234372138977]}, "name": "MET_SoftTrk_ResoPerp", "type": "histosys"}, {"data": {"hi_data": [0.48643234372138977], "lo_data": [0.48643234372138977]}, "name": "MUON_ID", "type": "histosys"}, {"data": {"hi_data": [0.48643234372138977], "lo_data": [0.48643234372138977]}, "name": "MUON_MS", "type": "histosys"}, {"data": {"hi_data": [0.48643234372138977], "lo_data": [0.48643234372138977]}, "name": "MUON_SAGITTA_RESBIAS", "type": "histosys"}, {"data": {"hi_data": [0.48643234372138977], "lo_data": [0.48643234372138977]}, "name": "MUON_SAGITTA_RHO", "type": "histosys"}, {"data": {"hi_data": [0.48643234372138977], "lo_data": [0.48643234372138977]}, "name": "MUON_SCALE", "type": "histosys"}, {"data": {"hi": 1.01836, "lo": 0.981898}, "name": "JVT", "type": "normsys"}, {"data": {"hi": 1.00165, "lo": 0.998349}, "name": "MUON_Eff_Iso_stat", "type": "normsys"}, {"data": {"hi": 1.00356, "lo": 0.996437}, "name": "MUON_Eff_Iso_sys", "type": "normsys"}, {"data": {"hi": 1.00055, "lo": 0.999454}, "name": "MUON_Eff_stat", "type": "normsys"}, {"data": {"hi": 1.00275, "lo": 0.997255}, "name": "MUON_Eff_sys", "type": "normsys"}, {"data": {"hi": 1.00034, "lo": 0.999664}, "name": "MUON_TTVA_stat", "type": "normsys"}, {"data": {"hi": 1.00061, "lo": 0.999388}, "name": "MUON_TTVA_sys", "type": "normsys"}, {"data": {"hi": 1.05347, "lo": 0.946535}, "name": "SigXSec", "type": "normsys"}, {"data": {"hi": 1.02164, "lo": 0.978591}, "name": "btag_BT", "type": "normsys"}, {"data": {"hi": 0.99074, "lo": 1.00932}, "name": "btag_LightT", "type": "normsys"}, {"data": {"hi": 1.11728, "lo": 0.955418}, "name": "pileup", "type": "normsys"}, {"data": {"hi": 0.99928, "lo": 1.00072}, "name": "JER_DataVsMC", "type": "normsys"}, {"data": {"hi": 1.00072, "lo": 0.99928}, "name": "JER_EffectiveNP_1", "type": "normsys"}, {"data": {"hi": 1.00072, "lo": 0.99928}, "name": "JER_EffectiveNP_10", "type": "normsys"}, {"data": {"hi": 1.00072, "lo": 0.99928}, "name": "JER_EffectiveNP_11", "type": "normsys"}, {"data": {"hi": 1.00072, "lo": 0.99928}, "name": "JER_EffectiveNP_12restTerm", "type": "normsys"}, {"data": {"hi": 0.99928, "lo": 1.00072}, "name": "JER_EffectiveNP_2", "type": "normsys"}, {"data": {"hi": 1.00072, "lo": 0.99928}, "name": "JER_EffectiveNP_3", "type": "normsys"}, {"data": {"hi": 1.00072, "lo": 0.99928}, "name": "JER_EffectiveNP_4", "type": "normsys"}, {"data": {"hi": 1.00072, "lo": 0.99928}, "name": "JER_EffectiveNP_5", "type": "normsys"}, {"data": {"hi": 0.99928, "lo": 1.00072}, "name": "JER_EffectiveNP_9", "type": "normsys"}, {"data": {"hi": 0.99928, "lo": 1.00072}, "name": "JES_EffectiveNP_Modelling1", "type": "normsys"}, {"data": {"hi": 1.00072, "lo": 0.99928}, "name": "JES_EffectiveNP_Modelling2", "type": "normsys"}, {"data": {"hi": 1.00072, "lo": 0.99928}, "name": "JES_EffectiveNP_Statistical2", "type": "normsys"}, {"data": {"hi": 0.99928, "lo": 1.00072}, "name": "JES_EtaIntercalibration_Modelling", "type": "normsys"}, {"data": {"hi": 0.99928, "lo": 1.00072}, "name": "JES_EtaIntercalibration_TotalStat", "type": "normsys"}, {"data": {"hi": 0.99928, "lo": 1.00072}, "name": "JES_Flavor_Composition", "type": "normsys"}, {"data": {"hi": 1.00072, "lo": 0.99928}, "name": "JES_Flavor_Response", "type": "normsys"}, {"data": {"hi": 0.99928, "lo": 1.00072}, "name": "JES_Pileup_OffsetMu", "type": "normsys"}, {"data": {"hi": 0.99928, "lo": 1.00072}, "name": "JES_Pileup_OffsetNPV", "type": "normsys"}, {"data": {"hi": 0.99928, "lo": 1.00072}, "name": "JES_Pileup_RhoTopology", "type": "normsys"}, {"data": {"hi": 1.02, "lo": 0.98}, "name": "trigger", "type": "normsys"}, {"data": null, "name": "mu_SIG", "type": "normfactor"}], "name": "C1N2_Wh_hbb_250_75"}}, {"op": "add", "path": "/channels/2/samples/9", "value": {"data": [0.5448289513587952], "modifiers": [{"data": null, "name": "lumi", "type": "lumi"}, {"data": [0.5448289661024008], "name": "staterror_TRHMEM_cuts", "type": "staterror"}, {"data": {"hi_data": [0.5448289513587952], "lo_data": [0.5448289513587952]}, "name": "EG_Eff", "type": "histosys"}, {"data": {"hi_data": [0.5448289513587952], "lo_data": [0.5448289513587952]}, "name": "EG_Iso", "type": "histosys"}, {"data": {"hi_data": [0.5448289513587952], "lo_data": [0.5448289513587952]}, "name": "EG_Reco", "type": "histosys"}, {"data": {"hi_data": [0.5448289513587952], "lo_data": [0.5448289513587952]}, "name": "JVT", "type": "histosys"}, {"data": {"hi_data": [0.5448289513587952], "lo_data": [0.5448289513587952]}, "name": "MUON_Eff_BadMuon_stat", "type": "histosys"}, {"data": {"hi_data": [0.5448289513587952], "lo_data": [0.5448289513587952]}, "name": "MUON_Eff_BadMuon_sys", "type": "histosys"}, {"data": {"hi_data": [0.5448289513587952], "lo_data": [0.5448289513587952]}, "name": "MUON_Eff_Iso_stat", "type": "histosys"}, {"data": {"hi_data": [0.5448289513587952], "lo_data": [0.5448289513587952]}, "name": "MUON_Eff_Iso_sys", "type": "histosys"}, {"data": {"hi_data": [0.5448289513587952], "lo_data": [0.5448289513587952]}, "name": "MUON_Eff_stat", "type": "histosys"}, {"data": {"hi_data": [0.5448289513587952], "lo_data": [0.5448289513587952]}, "name": "MUON_Eff_stat_lowpt", "type": "histosys"}, {"data": {"hi_data": [0.5448289513587952], "lo_data": [0.5448289513587952]}, "name": "MUON_Eff_sys", "type": "histosys"}, {"data": {"hi_data": [0.5448289513587952], "lo_data": [0.5448289513587952]}, "name": "MUON_Eff_sys_lowpt", "type": "histosys"}, {"data": {"hi_data": [0.5448289513587952], "lo_data": [0.5448289513587952]}, "name": "MUON_TTVA_stat", "type": "histosys"}, {"data": {"hi_data": [0.5448289513587952], "lo_data": [0.5448289513587952]}, "name": "MUON_TTVA_sys", "type": "histosys"}, {"data": {"hi_data": [0.5448289513587952], "lo_data": [0.5448289513587952]}, "name": "btag_BT", "type": "histosys"}, {"data": {"hi_data": [0.5448289513587952], "lo_data": [0.5448289513587952]}, "name": "btag_CT", "type": "histosys"}, {"data": {"hi_data": [0.5448289513587952], "lo_data": [0.5448289513587952]}, "name": "btag_Extra", "type": "histosys"}, {"data": {"hi_data": [0.5448289513587952], "lo_data": [0.5448289513587952]}, "name": "btag_ExtraFromCharm", "type": "histosys"}, {"data": {"hi_data": [0.5448289513587952], "lo_data": [0.5448289513587952]}, "name": "btag_LightT", "type": "histosys"}, {"data": {"hi_data": [0.5448289513587952], "lo_data": [0.5448289513587952]}, "name": "pileup", "type": "histosys"}, {"data": {"hi_data": [0.5448289513587952], "lo_data": [0.5448289513587952]}, "name": "EG_RESOLUTION_ALL", "type": "histosys"}, {"data": {"hi_data": [0.5448289513587952], "lo_data": [0.5448289513587952]}, "name": "EG_SCALE_AF2", "type": "histosys"}, {"data": {"hi_data": [0.5448289513587952], "lo_data": [0.5448289513587952]}, "name": "EG_SCALE_ALL", "type": "histosys"}, {"data": {"hi_data": [0.5448289513587952], "lo_data": [0.5448289513587952]}, "name": "JER_DataVsMC", "type": "histosys"}, {"data": {"hi_data": [0.5448289513587952], "lo_data": [0.5448289513587952]}, "name": "JER_EffectiveNP_1", "type": "histosys"}, {"data": {"hi_data": [0.5448289513587952], "lo_data": [0.5448289513587952]}, "name": "JER_EffectiveNP_10", "type": "histosys"}, {"data": {"hi_data": [0.5448289513587952], "lo_data": [0.5448289513587952]}, "name": "JER_EffectiveNP_11", "type": "histosys"}, {"data": {"hi_data": [0.5448289513587952], "lo_data": [0.5448289513587952]}, "name": "JER_EffectiveNP_12restTerm", "type": "histosys"}, {"data": {"hi_data": [0.5448289513587952], "lo_data": [0.5448289513587952]}, "name": "JER_EffectiveNP_2", "type": "histosys"}, {"data": {"hi_data": [0.5448289513587952], "lo_data": [0.5448289513587952]}, "name": "JER_EffectiveNP_3", "type": "histosys"}, {"data": {"hi_data": [0.5448289513587952], "lo_data": [0.5448289513587952]}, "name": "JER_EffectiveNP_4", "type": "histosys"}, {"data": {"hi_data": [0.5448289513587952], "lo_data": [0.5448289513587952]}, "name": "JER_EffectiveNP_5", "type": "histosys"}, {"data": {"hi_data": [0.5448289513587952], "lo_data": [0.5448289513587952]}, "name": "JER_EffectiveNP_6", "type": "histosys"}, {"data": {"hi_data": [0.5448289513587952], "lo_data": [0.5448289513587952]}, "name": "JER_EffectiveNP_7", "type": "histosys"}, {"data": {"hi_data": [0.5448289513587952], "lo_data": [0.5448289513587952]}, "name": "JER_EffectiveNP_8", "type": "histosys"}, {"data": {"hi_data": [0.5448289513587952], "lo_data": [0.5448289513587952]}, "name": "JER_EffectiveNP_9", "type": "histosys"}, {"data": {"hi_data": [0.5448289513587952], "lo_data": [0.5448289513587952]}, "name": "JES_BJES_Response", "type": "histosys"}, {"data": {"hi_data": [0.5448289513587952], "lo_data": [0.5448289513587952]}, "name": "JES_Comb_Baseline_Kin", "type": "histosys"}, {"data": {"hi_data": [0.5448289513587952], "lo_data": [0.5448289513587952]}, "name": "JES_Comb_Modelling_Kin", "type": "histosys"}, {"data": {"hi_data": [0.5448289513587952], "lo_data": [0.5448289513587952]}, "name": "JES_Comb_TotalStat_Kin", "type": "histosys"}, {"data": {"hi_data": [0.5448289513587952], "lo_data": [0.5448289513587952]}, "name": "JES_Comb_Tracking_Kin", "type": "histosys"}, {"data": {"hi_data": [0.5448289513587952], "lo_data": [0.5448289513587952]}, "name": "JES_EffectiveNP_Detector1", "type": "histosys"}, {"data": {"hi_data": [0.5448289513587952], "lo_data": [0.5448289513587952]}, "name": "JES_EffectiveNP_Detector2", "type": "histosys"}, {"data": {"hi_data": [0.5448289513587952], "lo_data": [0.5448289513587952]}, "name": "JES_EffectiveNP_Mixed1", "type": "histosys"}, {"data": {"hi_data": [0.5448289513587952], "lo_data": [0.5448289513587952]}, "name": "JES_EffectiveNP_Mixed2", "type": "histosys"}, {"data": {"hi_data": [0.5448289513587952], "lo_data": [0.5448289513587952]}, "name": "JES_EffectiveNP_Mixed3", "type": "histosys"}, {"data": {"hi_data": [0.5448289513587952], "lo_data": [0.5448289513587952]}, "name": "JES_EffectiveNP_Modelling1", "type": "histosys"}, {"data": {"hi_data": [0.5448289513587952], "lo_data": [0.5448289513587952]}, "name": "JES_EffectiveNP_Modelling2", "type": "histosys"}, {"data": {"hi_data": [0.5448289513587952], "lo_data": [0.5448289513587952]}, "name": "JES_EffectiveNP_Modelling3", "type": "histosys"}, {"data": {"hi_data": [0.5448289513587952], "lo_data": [0.5448289513587952]}, "name": "JES_EffectiveNP_Modelling4", "type": "histosys"}, {"data": {"hi_data": [0.5448289513587952], "lo_data": [0.5448289513587952]}, "name": "JES_EffectiveNP_Statistical1", "type": "histosys"}, {"data": {"hi_data": [0.5448289513587952], "lo_data": [0.5448289513587952]}, "name": "JES_EffectiveNP_Statistical2", "type": "histosys"}, {"data": {"hi_data": [0.5448289513587952], "lo_data": [0.5448289513587952]}, "name": "JES_EffectiveNP_Statistical3", "type": "histosys"}, {"data": {"hi_data": [0.5448289513587952], "lo_data": [0.5448289513587952]}, "name": "JES_EffectiveNP_Statistical4", "type": "histosys"}, {"data": {"hi_data": [0.5448289513587952], "lo_data": [0.5448289513587952]}, "name": "JES_EffectiveNP_Statistical5", "type": "histosys"}, {"data": {"hi_data": [0.5448289513587952], "lo_data": [0.5448289513587952]}, "name": "JES_EffectiveNP_Statistical6", "type": "histosys"}, {"data": {"hi_data": [0.5448289513587952], "lo_data": [0.5448289513587952]}, "name": "JES_EtaIntercalibration_Modelling", "type": "histosys"}, {"data": {"hi_data": [0.5448289513587952], "lo_data": [0.5448289513587952]}, "name": "JES_EtaIntercalibration_NonClosure_highE", "type": "histosys"}, {"data": {"hi_data": [0.5448289513587952], "lo_data": [0.5448289513587952]}, "name": "JES_EtaIntercalibration_NonClosure_negEta", "type": "histosys"}, {"data": {"hi_data": [0.5448289513587952], "lo_data": [0.5448289513587952]}, "name": "JES_EtaIntercalibration_NonClosure_posEta", "type": "histosys"}, {"data": {"hi_data": [0.5448289513587952], "lo_data": [0.5448289513587952]}, "name": "JES_EtaIntercalibration_TotalStat", "type": "histosys"}, {"data": {"hi_data": [0.5448289513587952], "lo_data": [0.5448289513587952]}, "name": "JES_Flavor_Composition", "type": "histosys"}, {"data": {"hi_data": [0.5448289513587952], "lo_data": [0.5448289513587952]}, "name": "JES_Flavor_Response", "type": "histosys"}, {"data": {"hi_data": [0.5448289513587952], "lo_data": [0.5448289513587952]}, "name": "JES_Pileup_OffsetMu", "type": "histosys"}, {"data": {"hi_data": [0.5448289513587952], "lo_data": [0.5448289513587952]}, "name": "JES_Pileup_OffsetNPV", "type": "histosys"}, {"data": {"hi_data": [0.5448289513587952], "lo_data": [0.5448289513587952]}, "name": "JES_Pileup_PtTerm", "type": "histosys"}, {"data": {"hi_data": [0.5448289513587952], "lo_data": [0.5448289513587952]}, "name": "JES_Pileup_RhoTopology", "type": "histosys"}, {"data": {"hi_data": [0.5448289513587952], "lo_data": [0.5448289513587952]}, "name": "JES_SingleParticle_HighPt", "type": "histosys"}, {"data": {"hi_data": [0.5448289513587952], "lo_data": [0.5448289513587952]}, "name": "MET_SoftTrk", "type": "histosys"}, {"data": {"hi_data": [0.5448289513587952], "lo_data": [0.5448289513587952]}, "name": "MET_SoftTrk_ResoPara", "type": "histosys"}, {"data": {"hi_data": [0.5448289513587952], "lo_data": [0.5448289513587952]}, "name": "MET_SoftTrk_ResoPerp", "type": "histosys"}, {"data": {"hi_data": [0.5448289513587952], "lo_data": [0.5448289513587952]}, "name": "MUON_ID", "type": "histosys"}, {"data": {"hi_data": [0.5448289513587952], "lo_data": [0.5448289513587952]}, "name": "MUON_MS", "type": "histosys"}, {"data": {"hi_data": [0.5448289513587952], "lo_data": [0.5448289513587952]}, "name": "MUON_SAGITTA_RESBIAS", "type": "histosys"}, {"data": {"hi_data": [0.5448289513587952], "lo_data": [0.5448289513587952]}, "name": "MUON_SAGITTA_RHO", "type": "histosys"}, {"data": {"hi_data": [0.5448289513587952], "lo_data": [0.5448289513587952]}, "name": "MUON_SCALE", "type": "histosys"}, {"data": {"hi": 1.00474, "lo": 0.995267}, "name": "JVT", "type": "normsys"}, {"data": {"hi": 1.00015, "lo": 0.999847}, "name": "MUON_Eff_Iso_stat", "type": "normsys"}, {"data": {"hi": 1.002, "lo": 0.997999}, "name": "MUON_Eff_Iso_sys", "type": "normsys"}, {"data": {"hi": 1.00045, "lo": 0.999554}, "name": "MUON_Eff_stat", "type": "normsys"}, {"data": {"hi": 1.00219, "lo": 0.997815}, "name": "MUON_Eff_sys", "type": "normsys"}, {"data": {"hi": 1.00014, "lo": 0.999856}, "name": "MUON_TTVA_stat", "type": "normsys"}, {"data": {"hi": 1.00009, "lo": 0.999906}, "name": "MUON_TTVA_sys", "type": "normsys"}, {"data": {"hi": 1.07965, "lo": 0.920355}, "name": "SigXSec", "type": "normsys"}, {"data": {"hi": 1.02698, "lo": 0.973375}, "name": "btag_BT", "type": "normsys"}, {"data": {"hi": 0.99421, "lo": 1.00581}, "name": "btag_LightT", "type": "normsys"}, {"data": {"hi": 0.940484, "lo": 1.17445}, "name": "pileup", "type": "normsys"}, {"data": {"hi": 0.999436, "lo": 1.00056}, "name": "JES_Flavor_Composition", "type": "normsys"}, {"data": {"hi": 1.02, "lo": 0.98}, "name": "trigger", "type": "normsys"}, {"data": null, "name": "mu_SIG", "type": "normfactor"}], "name": "C1N2_Wh_hbb_250_75"}}, {"op": "add", "path": "/channels/3/samples/9", "value": {"data": [2.005208730697632], "modifiers": [{"data": null, "name": "lumi", "type": "lumi"}, {"data": [1.006843233760532], "name": "staterror_TRMMEM_cuts", "type": "staterror"}, {"data": {"hi_data": [2.005208730697632], "lo_data": [2.005208730697632]}, "name": "EG_Eff", "type": "histosys"}, {"data": {"hi_data": [2.005208730697632], "lo_data": [2.005208730697632]}, "name": "EG_Iso", "type": "histosys"}, {"data": {"hi_data": [2.005208730697632], "lo_data": [2.005208730697632]}, "name": "EG_Reco", "type": "histosys"}, {"data": {"hi_data": [2.005208730697632], "lo_data": [2.005208730697632]}, "name": "JVT", "type": "histosys"}, {"data": {"hi_data": [2.005208730697632], "lo_data": [2.005208730697632]}, "name": "MUON_Eff_BadMuon_stat", "type": "histosys"}, {"data": {"hi_data": [2.005208730697632], "lo_data": [2.005208730697632]}, "name": "MUON_Eff_BadMuon_sys", "type": "histosys"}, {"data": {"hi_data": [2.005208730697632], "lo_data": [2.005208730697632]}, "name": "MUON_Eff_Iso_stat", "type": "histosys"}, {"data": {"hi_data": [2.005208730697632], "lo_data": [2.005208730697632]}, "name": "MUON_Eff_Iso_sys", "type": "histosys"}, {"data": {"hi_data": [2.005208730697632], "lo_data": [2.005208730697632]}, "name": "MUON_Eff_stat", "type": "histosys"}, {"data": {"hi_data": [2.005208730697632], "lo_data": [2.005208730697632]}, "name": "MUON_Eff_stat_lowpt", "type": "histosys"}, {"data": {"hi_data": [2.005208730697632], "lo_data": [2.005208730697632]}, "name": "MUON_Eff_sys", "type": "histosys"}, {"data": {"hi_data": [2.005208730697632], "lo_data": [2.005208730697632]}, "name": "MUON_Eff_sys_lowpt", "type": "histosys"}, {"data": {"hi_data": [2.005208730697632], "lo_data": [2.005208730697632]}, "name": "MUON_TTVA_stat", "type": "histosys"}, {"data": {"hi_data": [2.005208730697632], "lo_data": [2.005208730697632]}, "name": "MUON_TTVA_sys", "type": "histosys"}, {"data": {"hi_data": [2.005208730697632], "lo_data": [2.005208730697632]}, "name": "btag_BT", "type": "histosys"}, {"data": {"hi_data": [2.005208730697632], "lo_data": [2.005208730697632]}, "name": "btag_CT", "type": "histosys"}, {"data": {"hi_data": [2.005208730697632], "lo_data": [2.005208730697632]}, "name": "btag_Extra", "type": "histosys"}, {"data": {"hi_data": [2.005208730697632], "lo_data": [2.005208730697632]}, "name": "btag_ExtraFromCharm", "type": "histosys"}, {"data": {"hi_data": [2.005208730697632], "lo_data": [2.005208730697632]}, "name": "btag_LightT", "type": "histosys"}, {"data": {"hi_data": [2.005208730697632], "lo_data": [2.005208730697632]}, "name": "pileup", "type": "histosys"}, {"data": {"hi_data": [2.005208730697632], "lo_data": [2.005208730697632]}, "name": "EG_RESOLUTION_ALL", "type": "histosys"}, {"data": {"hi_data": [2.005208730697632], "lo_data": [2.005208730697632]}, "name": "EG_SCALE_AF2", "type": "histosys"}, {"data": {"hi_data": [2.005208730697632], "lo_data": [2.005208730697632]}, "name": "EG_SCALE_ALL", "type": "histosys"}, {"data": {"hi_data": [2.005208730697632], "lo_data": [2.005208730697632]}, "name": "JER_DataVsMC", "type": "histosys"}, {"data": {"hi_data": [2.005208730697632], "lo_data": [2.005208730697632]}, "name": "JER_EffectiveNP_1", "type": "histosys"}, {"data": {"hi_data": [2.005208730697632], "lo_data": [2.005208730697632]}, "name": "JER_EffectiveNP_10", "type": "histosys"}, {"data": {"hi_data": [2.005208730697632], "lo_data": [2.005208730697632]}, "name": "JER_EffectiveNP_11", "type": "histosys"}, {"data": {"hi_data": [2.005208730697632], "lo_data": [2.005208730697632]}, "name": "JER_EffectiveNP_12restTerm", "type": "histosys"}, {"data": {"hi_data": [2.005208730697632], "lo_data": [2.005208730697632]}, "name": "JER_EffectiveNP_2", "type": "histosys"}, {"data": {"hi_data": [2.005208730697632], "lo_data": [2.005208730697632]}, "name": "JER_EffectiveNP_3", "type": "histosys"}, {"data": {"hi_data": [2.005208730697632], "lo_data": [2.005208730697632]}, "name": "JER_EffectiveNP_4", "type": "histosys"}, {"data": {"hi_data": [2.005208730697632], "lo_data": [2.005208730697632]}, "name": "JER_EffectiveNP_5", "type": "histosys"}, {"data": {"hi_data": [2.005208730697632], "lo_data": [2.005208730697632]}, "name": "JER_EffectiveNP_6", "type": "histosys"}, {"data": {"hi_data": [2.005208730697632], "lo_data": [2.005208730697632]}, "name": "JER_EffectiveNP_7", "type": "histosys"}, {"data": {"hi_data": [2.005208730697632], "lo_data": [2.005208730697632]}, "name": "JER_EffectiveNP_8", "type": "histosys"}, {"data": {"hi_data": [2.005208730697632], "lo_data": [2.005208730697632]}, "name": "JER_EffectiveNP_9", "type": "histosys"}, {"data": {"hi_data": [2.005208730697632], "lo_data": [2.005208730697632]}, "name": "JES_BJES_Response", "type": "histosys"}, {"data": {"hi_data": [2.005208730697632], "lo_data": [2.005208730697632]}, "name": "JES_Comb_Baseline_Kin", "type": "histosys"}, {"data": {"hi_data": [2.005208730697632], "lo_data": [2.005208730697632]}, "name": "JES_Comb_Modelling_Kin", "type": "histosys"}, {"data": {"hi_data": [2.005208730697632], "lo_data": [2.005208730697632]}, "name": "JES_Comb_TotalStat_Kin", "type": "histosys"}, {"data": {"hi_data": [2.005208730697632], "lo_data": [2.005208730697632]}, "name": "JES_Comb_Tracking_Kin", "type": "histosys"}, {"data": {"hi_data": [2.005208730697632], "lo_data": [2.005208730697632]}, "name": "JES_EffectiveNP_Detector1", "type": "histosys"}, {"data": {"hi_data": [2.005208730697632], "lo_data": [2.005208730697632]}, "name": "JES_EffectiveNP_Detector2", "type": "histosys"}, {"data": {"hi_data": [2.005208730697632], "lo_data": [2.005208730697632]}, "name": "JES_EffectiveNP_Mixed1", "type": "histosys"}, {"data": {"hi_data": [2.005208730697632], "lo_data": [2.005208730697632]}, "name": "JES_EffectiveNP_Mixed2", "type": "histosys"}, {"data": {"hi_data": [2.005208730697632], "lo_data": [2.005208730697632]}, "name": "JES_EffectiveNP_Mixed3", "type": "histosys"}, {"data": {"hi_data": [2.005208730697632], "lo_data": [2.005208730697632]}, "name": "JES_EffectiveNP_Modelling1", "type": "histosys"}, {"data": {"hi_data": [2.005208730697632], "lo_data": [2.005208730697632]}, "name": "JES_EffectiveNP_Modelling2", "type": "histosys"}, {"data": {"hi_data": [2.005208730697632], "lo_data": [2.005208730697632]}, "name": "JES_EffectiveNP_Modelling3", "type": "histosys"}, {"data": {"hi_data": [2.005208730697632], "lo_data": [2.005208730697632]}, "name": "JES_EffectiveNP_Modelling4", "type": "histosys"}, {"data": {"hi_data": [2.005208730697632], "lo_data": [2.005208730697632]}, "name": "JES_EffectiveNP_Statistical1", "type": "histosys"}, {"data": {"hi_data": [2.005208730697632], "lo_data": [2.005208730697632]}, "name": "JES_EffectiveNP_Statistical2", "type": "histosys"}, {"data": {"hi_data": [2.005208730697632], "lo_data": [2.005208730697632]}, "name": "JES_EffectiveNP_Statistical3", "type": "histosys"}, {"data": {"hi_data": [2.005208730697632], "lo_data": [2.005208730697632]}, "name": "JES_EffectiveNP_Statistical4", "type": "histosys"}, {"data": {"hi_data": [2.005208730697632], "lo_data": [2.005208730697632]}, "name": "JES_EffectiveNP_Statistical5", "type": "histosys"}, {"data": {"hi_data": [2.005208730697632], "lo_data": [2.005208730697632]}, "name": "JES_EffectiveNP_Statistical6", "type": "histosys"}, {"data": {"hi_data": [2.005208730697632], "lo_data": [2.005208730697632]}, "name": "JES_EtaIntercalibration_Modelling", "type": "histosys"}, {"data": {"hi_data": [2.005208730697632], "lo_data": [2.005208730697632]}, "name": "JES_EtaIntercalibration_NonClosure_highE", "type": "histosys"}, {"data": {"hi_data": [2.005208730697632], "lo_data": [2.005208730697632]}, "name": "JES_EtaIntercalibration_NonClosure_negEta", "type": "histosys"}, {"data": {"hi_data": [2.005208730697632], "lo_data": [2.005208730697632]}, "name": "JES_EtaIntercalibration_NonClosure_posEta", "type": "histosys"}, {"data": {"hi_data": [2.005208730697632], "lo_data": [2.005208730697632]}, "name": "JES_EtaIntercalibration_TotalStat", "type": "histosys"}, {"data": {"hi_data": [2.005208730697632], "lo_data": [2.005208730697632]}, "name": "JES_Flavor_Composition", "type": "histosys"}, {"data": {"hi_data": [2.005208730697632], "lo_data": [2.005208730697632]}, "name": "JES_Flavor_Response", "type": "histosys"}, {"data": {"hi_data": [2.005208730697632], "lo_data": [2.005208730697632]}, "name": "JES_Pileup_OffsetMu", "type": "histosys"}, {"data": {"hi_data": [2.005208730697632], "lo_data": [2.005208730697632]}, "name": "JES_Pileup_OffsetNPV", "type": "histosys"}, {"data": {"hi_data": [2.005208730697632], "lo_data": [2.005208730697632]}, "name": "JES_Pileup_PtTerm", "type": "histosys"}, {"data": {"hi_data": [2.005208730697632], "lo_data": [2.005208730697632]}, "name": "JES_Pileup_RhoTopology", "type": "histosys"}, {"data": {"hi_data": [2.005208730697632], "lo_data": [2.005208730697632]}, "name": "JES_SingleParticle_HighPt", "type": "histosys"}, {"data": {"hi_data": [2.005208730697632], "lo_data": [2.005208730697632]}, "name": "MET_SoftTrk", "type": "histosys"}, {"data": {"hi_data": [2.005208730697632], "lo_data": [2.005208730697632]}, "name": "MET_SoftTrk_ResoPara", "type": "histosys"}, {"data": {"hi_data": [2.005208730697632], "lo_data": [2.005208730697632]}, "name": "MET_SoftTrk_ResoPerp", "type": "histosys"}, {"data": {"hi_data": [2.005208730697632], "lo_data": [2.005208730697632]}, "name": "MUON_ID", "type": "histosys"}, {"data": {"hi_data": [2.005208730697632], "lo_data": [2.005208730697632]}, "name": "MUON_MS", "type": "histosys"}, {"data": {"hi_data": [2.005208730697632], "lo_data": [2.005208730697632]}, "name": "MUON_SAGITTA_RESBIAS", "type": "histosys"}, {"data": {"hi_data": [2.005208730697632], "lo_data": [2.005208730697632]}, "name": "MUON_SAGITTA_RHO", "type": "histosys"}, {"data": {"hi_data": [2.005208730697632], "lo_data": [2.005208730697632]}, "name": "MUON_SCALE", "type": "histosys"}, {"data": {"hi": 1.00193, "lo": 0.998065}, "name": "EG_Eff", "type": "normsys"}, {"data": {"hi": 1.00009, "lo": 0.999906}, "name": "EG_Iso", "type": "normsys"}, {"data": {"hi": 1.0004, "lo": 0.999598}, "name": "EG_Reco", "type": "normsys"}, {"data": {"hi": 1.0073, "lo": 0.992737}, "name": "JVT", "type": "normsys"}, {"data": {"hi": 1.00001, "lo": 0.999989}, "name": "MUON_Eff_Iso_stat", "type": "normsys"}, {"data": {"hi": 1.00096, "lo": 0.999038}, "name": "MUON_Eff_Iso_sys", "type": "normsys"}, {"data": {"hi": 1.00059, "lo": 0.999409}, "name": "MUON_Eff_stat", "type": "normsys"}, {"data": {"hi": 1.00284, "lo": 0.997162}, "name": "MUON_Eff_sys", "type": "normsys"}, {"data": {"hi": 1.00015, "lo": 0.999854}, "name": "MUON_TTVA_stat", "type": "normsys"}, {"data": {"hi": 1.00002, "lo": 0.99998}, "name": "MUON_TTVA_sys", "type": "normsys"}, {"data": {"hi": 1.05908, "lo": 0.940922}, "name": "SigXSec", "type": "normsys"}, {"data": {"hi": 1.03617, "lo": 0.96437}, "name": "btag_BT", "type": "normsys"}, {"data": {"hi": 0.998075, "lo": 1.00192}, "name": "btag_LightT", "type": "normsys"}, {"data": {"hi": 0.963189, "lo": 1.00683}, "name": "pileup", "type": "normsys"}, {"data": {"hi": 1.07152, "lo": 0.928479}, "name": "JER_EffectiveNP_1", "type": "normsys"}, {"data": {"hi": 1.25341, "lo": 0.746585}, "name": "JER_EffectiveNP_10", "type": "normsys"}, {"data": {"hi": 0.928479, "lo": 1.07152}, "name": "JER_EffectiveNP_2", "type": "normsys"}, {"data": {"hi": 1.29883, "lo": 1.50088}, "name": "JER_EffectiveNP_3", "type": "normsys"}, {"data": {"hi": 1.01292, "lo": 0.98708}, "name": "JER_EffectiveNP_4", "type": "normsys"}, {"data": {"hi": 0.98708, "lo": 1.01292}, "name": "JER_EffectiveNP_5", "type": "normsys"}, {"data": {"hi": 1.01292, "lo": 0.98708}, "name": "JER_EffectiveNP_6", "type": "normsys"}, {"data": {"hi": 1.48072, "lo": 0.519279}, "name": "JES_EffectiveNP_Modelling1", "type": "normsys"}, {"data": {"hi": 1.48072, "lo": 0.519279}, "name": "JES_Flavor_Composition", "type": "normsys"}, {"data": {"hi": 0.519279, "lo": 1.48072}, "name": "JES_Flavor_Response", "type": "normsys"}, {"data": {"hi": 1.02, "lo": 0.98}, "name": "trigger", "type": "normsys"}, {"data": null, "name": "mu_SIG", "type": "normfactor"}], "name": "C1N2_Wh_hbb_250_75"}}, {"op": "add", "path": "/channels/5/samples/7", "value": {"data": [0.0, 0.0, 0.7211554050445557], "modifiers": [{"data": null, "name": "lumi", "type": "lumi"}, {"data": [0.0, 0.0, 0.7211554088958361], "name": "staterror_SRHMEM_mct2", "type": "staterror"}, {"data": {"hi_data": [0.0, 0.0, 0.7211554050445557], "lo_data": [0.0, 0.0, 0.7211554050445557]}, "name": "EG_Eff", "type": "histosys"}, {"data": {"hi_data": [0.0, 0.0, 0.7211554050445557], "lo_data": [0.0, 0.0, 0.7211554050445557]}, "name": "EG_Iso", "type": "histosys"}, {"data": {"hi_data": [0.0, 0.0, 0.7211554050445557], "lo_data": [0.0, 0.0, 0.7211554050445557]}, "name": "EG_Reco", "type": "histosys"}, {"data": {"hi_data": [0.0, 0.0, 0.7211554050445557], "lo_data": [0.0, 0.0, 0.7211554050445557]}, "name": "JVT", "type": "histosys"}, {"data": {"hi_data": [0.0, 0.0, 0.7211554050445557], "lo_data": [0.0, 0.0, 0.7211554050445557]}, "name": "MUON_Eff_BadMuon_stat", "type": "histosys"}, {"data": {"hi_data": [0.0, 0.0, 0.7211554050445557], "lo_data": [0.0, 0.0, 0.7211554050445557]}, "name": "MUON_Eff_BadMuon_sys", "type": "histosys"}, {"data": {"hi_data": [0.0, 0.0, 0.7211554050445557], "lo_data": [0.0, 0.0, 0.7211554050445557]}, "name": "MUON_Eff_Iso_stat", "type": "histosys"}, {"data": {"hi_data": [0.0, 0.0, 0.7211554050445557], "lo_data": [0.0, 0.0, 0.7211554050445557]}, "name": "MUON_Eff_Iso_sys", "type": "histosys"}, {"data": {"hi_data": [0.0, 0.0, 0.7211554050445557], "lo_data": [0.0, 0.0, 0.7211554050445557]}, "name": "MUON_Eff_stat", "type": "histosys"}, {"data": {"hi_data": [0.0, 0.0, 0.7211554050445557], "lo_data": [0.0, 0.0, 0.7211554050445557]}, "name": "MUON_Eff_stat_lowpt", "type": "histosys"}, {"data": {"hi_data": [0.0, 0.0, 0.7211554050445557], "lo_data": [0.0, 0.0, 0.7211554050445557]}, "name": "MUON_Eff_sys", "type": "histosys"}, {"data": {"hi_data": [0.0, 0.0, 0.7211554050445557], "lo_data": [0.0, 0.0, 0.7211554050445557]}, "name": "MUON_Eff_sys_lowpt", "type": "histosys"}, {"data": {"hi_data": [0.0, 0.0, 0.7211554050445557], "lo_data": [0.0, 0.0, 0.7211554050445557]}, "name": "MUON_TTVA_stat", "type": "histosys"}, {"data": {"hi_data": [0.0, 0.0, 0.7211554050445557], "lo_data": [0.0, 0.0, 0.7211554050445557]}, "name": "MUON_TTVA_sys", "type": "histosys"}, {"data": {"hi_data": [0.0, 0.0, 0.7211554050445557], "lo_data": [0.0, 0.0, 0.7211554050445557]}, "name": "btag_BT", "type": "histosys"}, {"data": {"hi_data": [0.0, 0.0, 0.7211554050445557], "lo_data": [0.0, 0.0, 0.7211554050445557]}, "name": "btag_CT", "type": "histosys"}, {"data": {"hi_data": [0.0, 0.0, 0.7211554050445557], "lo_data": [0.0, 0.0, 0.7211554050445557]}, "name": "btag_Extra", "type": "histosys"}, {"data": {"hi_data": [0.0, 0.0, 0.7211554050445557], "lo_data": [0.0, 0.0, 0.7211554050445557]}, "name": "btag_ExtraFromCharm", "type": "histosys"}, {"data": {"hi_data": [0.0, 0.0, 0.7211554050445557], "lo_data": [0.0, 0.0, 0.7211554050445557]}, "name": "btag_LightT", "type": "histosys"}, {"data": {"hi_data": [0.0, 0.0, 0.7211554050445557], "lo_data": [0.0, 0.0, 0.7211554050445557]}, "name": "pileup", "type": "histosys"}, {"data": {"hi_data": [0.0, 0.0, 0.7211554050445557], "lo_data": [0.0, 0.0, 0.7211554050445557]}, "name": "EG_RESOLUTION_ALL", "type": "histosys"}, {"data": {"hi_data": [0.0, 0.0, 0.7211554050445557], "lo_data": [0.0, 0.0, 0.7211554050445557]}, "name": "EG_SCALE_AF2", "type": "histosys"}, {"data": {"hi_data": [0.0, 0.0, 0.7211554050445557], "lo_data": [0.0, 0.0, 0.7211554050445557]}, "name": "EG_SCALE_ALL", "type": "histosys"}, {"data": {"hi_data": [0.0, 0.0, 0.7211554050445557], "lo_data": [0.0, 0.0, 0.7211554050445557]}, "name": "JER_DataVsMC", "type": "histosys"}, {"data": {"hi_data": [0.0, 0.3128047287464142, 0.4083506762981415], "lo_data": [0.0, 0.0, 0.7211554050445557]}, "name": "JER_EffectiveNP_1", "type": "histosys"}, {"data": {"hi_data": [0.0, 0.0, 0.7211554050445557], "lo_data": [0.0, 0.0, 0.7211554050445557]}, "name": "JER_EffectiveNP_10", "type": "histosys"}, {"data": {"hi_data": [0.0, 0.0, 0.7211554050445557], "lo_data": [0.0, 0.0, 0.7211554050445557]}, "name": "JER_EffectiveNP_11", "type": "histosys"}, {"data": {"hi_data": [0.0, 0.0, 0.7211554050445557], "lo_data": [0.0, 0.0, 0.7211554050445557]}, "name": "JER_EffectiveNP_12restTerm", "type": "histosys"}, {"data": {"hi_data": [0.0, 0.0, 0.7211554050445557], "lo_data": [0.0, 0.3128047287464142, 0.4083506762981415]}, "name": "JER_EffectiveNP_2", "type": "histosys"}, {"data": {"hi_data": [0.0, 0.0, 0.7211554050445557], "lo_data": [0.0, 0.0, 0.7211554050445557]}, "name": "JER_EffectiveNP_3", "type": "histosys"}, {"data": {"hi_data": [0.0, 0.0, 0.7211554050445557], "lo_data": [0.0, 0.0, 0.7211554050445557]}, "name": "JER_EffectiveNP_4", "type": "histosys"}, {"data": {"hi_data": [0.0, 0.0, 0.7211554050445557], "lo_data": [0.0, 0.0, 0.7211554050445557]}, "name": "JER_EffectiveNP_5", "type": "histosys"}, {"data": {"hi_data": [0.0, 0.0, 0.7211554050445557], "lo_data": [0.0, 0.0, 0.7211554050445557]}, "name": "JER_EffectiveNP_6", "type": "histosys"}, {"data": {"hi_data": [0.0, 0.0, 0.7211554050445557], "lo_data": [0.0, 0.0, 0.7211554050445557]}, "name": "JER_EffectiveNP_7", "type": "histosys"}, {"data": {"hi_data": [0.0, 0.0, 0.7211554050445557], "lo_data": [0.0, 0.0, 0.7211554050445557]}, "name": "JER_EffectiveNP_8", "type": "histosys"}, {"data": {"hi_data": [0.0, 0.0, 0.7211554050445557], "lo_data": [0.0, 0.0, 0.7211554050445557]}, "name": "JER_EffectiveNP_9", "type": "histosys"}, {"data": {"hi_data": [0.0, 0.0, 0.7211554050445557], "lo_data": [0.0, 0.0, 0.7211554050445557]}, "name": "JES_BJES_Response", "type": "histosys"}, {"data": {"hi_data": [0.0, 0.0, 0.7211554050445557], "lo_data": [0.0, 0.0, 0.7211554050445557]}, "name": "JES_Comb_Baseline_Kin", "type": "histosys"}, {"data": {"hi_data": [0.0, 0.0, 0.7211554050445557], "lo_data": [0.0, 0.0, 0.7211554050445557]}, "name": "JES_Comb_Modelling_Kin", "type": "histosys"}, {"data": {"hi_data": [0.0, 0.0, 0.7211554050445557], "lo_data": [0.0, 0.0, 0.7211554050445557]}, "name": "JES_Comb_TotalStat_Kin", "type": "histosys"}, {"data": {"hi_data": [0.0, 0.0, 0.7211554050445557], "lo_data": [0.0, 0.0, 0.7211554050445557]}, "name": "JES_Comb_Tracking_Kin", "type": "histosys"}, {"data": {"hi_data": [0.0, 0.0, 0.7211554050445557], "lo_data": [0.0, 0.0, 0.7211554050445557]}, "name": "JES_EffectiveNP_Detector1", "type": "histosys"}, {"data": {"hi_data": [0.0, 0.0, 0.7211554050445557], "lo_data": [0.0, 0.0, 0.7211554050445557]}, "name": "JES_EffectiveNP_Detector2", "type": "histosys"}, {"data": {"hi_data": [0.0, 0.0, 0.7211554050445557], "lo_data": [0.0, 0.0, 0.7211554050445557]}, "name": "JES_EffectiveNP_Mixed1", "type": "histosys"}, {"data": {"hi_data": [0.0, 0.0, 0.7211554050445557], "lo_data": [0.0, 0.0, 0.7211554050445557]}, "name": "JES_EffectiveNP_Mixed2", "type": "histosys"}, {"data": {"hi_data": [0.0, 0.0, 0.7211554050445557], "lo_data": [0.0, 0.0, 0.7211554050445557]}, "name": "JES_EffectiveNP_Mixed3", "type": "histosys"}, {"data": {"hi_data": [0.0, 0.0, 0.7211554050445557], "lo_data": [0.0, 0.0, 0.7211554050445557]}, "name": "JES_EffectiveNP_Modelling1", "type": "histosys"}, {"data": {"hi_data": [0.0, 0.0, 0.7211554050445557], "lo_data": [0.0, 0.0, 0.7211554050445557]}, "name": "JES_EffectiveNP_Modelling2", "type": "histosys"}, {"data": {"hi_data": [0.0, 0.0, 0.7211554050445557], "lo_data": [0.0, 0.0, 0.7211554050445557]}, "name": "JES_EffectiveNP_Modelling3", "type": "histosys"}, {"data": {"hi_data": [0.0, 0.0, 0.7211554050445557], "lo_data": [0.0, 0.0, 0.7211554050445557]}, "name": "JES_EffectiveNP_Modelling4", "type": "histosys"}, {"data": {"hi_data": [0.0, 0.0, 0.7211554050445557], "lo_data": [0.0, 0.0, 0.7211554050445557]}, "name": "JES_EffectiveNP_Statistical1", "type": "histosys"}, {"data": {"hi_data": [0.0, 0.0, 0.7211554050445557], "lo_data": [0.0, 0.0, 0.7211554050445557]}, "name": "JES_EffectiveNP_Statistical2", "type": "histosys"}, {"data": {"hi_data": [0.0, 0.0, 0.7211554050445557], "lo_data": [0.0, 0.0, 0.7211554050445557]}, "name": "JES_EffectiveNP_Statistical3", "type": "histosys"}, {"data": {"hi_data": [0.0, 0.0, 0.7211554050445557], "lo_data": [0.0, 0.0, 0.7211554050445557]}, "name": "JES_EffectiveNP_Statistical4", "type": "histosys"}, {"data": {"hi_data": [0.0, 0.0, 0.7211554050445557], "lo_data": [0.0, 0.0, 0.7211554050445557]}, "name": "JES_EffectiveNP_Statistical5", "type": "histosys"}, {"data": {"hi_data": [0.0, 0.0, 0.7211554050445557], "lo_data": [0.0, 0.0, 0.7211554050445557]}, "name": "JES_EffectiveNP_Statistical6", "type": "histosys"}, {"data": {"hi_data": [0.0, 0.0, 0.7211554050445557], "lo_data": [0.0, 0.0, 0.7211554050445557]}, "name": "JES_EtaIntercalibration_Modelling", "type": "histosys"}, {"data": {"hi_data": [0.0, 0.0, 0.7211554050445557], "lo_data": [0.0, 0.0, 0.7211554050445557]}, "name": "JES_EtaIntercalibration_NonClosure_highE", "type": "histosys"}, {"data": {"hi_data": [0.0, 0.0, 0.7211554050445557], "lo_data": [0.0, 0.0, 0.7211554050445557]}, "name": "JES_EtaIntercalibration_NonClosure_negEta", "type": "histosys"}, {"data": {"hi_data": [0.0, 0.0, 0.7211554050445557], "lo_data": [0.0, 0.0, 0.7211554050445557]}, "name": "JES_EtaIntercalibration_NonClosure_posEta", "type": "histosys"}, {"data": {"hi_data": [0.0, 0.0, 0.7211554050445557], "lo_data": [0.0, 0.0, 0.7211554050445557]}, "name": "JES_EtaIntercalibration_TotalStat", "type": "histosys"}, {"data": {"hi_data": [0.20630016922950745, 0.0, 0.5148552656173706], "lo_data": [0.0, 0.0, 0.7211554050445557]}, "name": "JES_Flavor_Composition", "type": "histosys"}, {"data": {"hi_data": [0.0, 0.0, 0.7211554050445557], "lo_data": [0.0, 0.0, 0.7211554050445557]}, "name": "JES_Flavor_Response", "type": "histosys"}, {"data": {"hi_data": [0.20630016922950745, 0.0, 0.5148552656173706], "lo_data": [0.0, 0.0, 0.7211554050445557]}, "name": "JES_Pileup_OffsetMu", "type": "histosys"}, {"data": {"hi_data": [0.0, 0.0, 0.7211554050445557], "lo_data": [0.0, 0.0, 0.7211554050445557]}, "name": "JES_Pileup_OffsetNPV", "type": "histosys"}, {"data": {"hi_data": [0.0, 0.0, 0.7211554050445557], "lo_data": [0.0, 0.0, 0.7211554050445557]}, "name": "JES_Pileup_PtTerm", "type": "histosys"}, {"data": {"hi_data": [0.0, 0.0, 0.7211554050445557], "lo_data": [0.0, 0.0, 0.7211554050445557]}, "name": "JES_Pileup_RhoTopology", "type": "histosys"}, {"data": {"hi_data": [0.0, 0.0, 0.7211554050445557], "lo_data": [0.0, 0.0, 0.7211554050445557]}, "name": "JES_SingleParticle_HighPt", "type": "histosys"}, {"data": {"hi_data": [0.0, 0.0, 0.7211554050445557], "lo_data": [0.0, 0.0, 0.7211554050445557]}, "name": "MET_SoftTrk", "type": "histosys"}, {"data": {"hi_data": [0.0, 0.0, 0.7211554050445557], "lo_data": [0.0, 0.0, 0.7211554050445557]}, "name": "MET_SoftTrk_ResoPara", "type": "histosys"}, {"data": {"hi_data": [0.0, 0.0, 0.7211554050445557], "lo_data": [0.0, 0.0, 0.7211554050445557]}, "name": "MET_SoftTrk_ResoPerp", "type": "histosys"}, {"data": {"hi_data": [0.0, 0.0, 0.7211554050445557], "lo_data": [0.0, 0.0, 0.7211554050445557]}, "name": "MUON_ID", "type": "histosys"}, {"data": {"hi_data": [0.0, 0.0, 0.7211554050445557], "lo_data": [0.0, 0.0, 0.7211554050445557]}, "name": "MUON_MS", "type": "histosys"}, {"data": {"hi_data": [0.0, 0.0, 0.7211554050445557], "lo_data": [0.0, 0.0, 0.7211554050445557]}, "name": "MUON_SAGITTA_RESBIAS", "type": "histosys"}, {"data": {"hi_data": [0.0, 0.0, 0.7211554050445557], "lo_data": [0.0, 0.0, 0.7211554050445557]}, "name": "MUON_SAGITTA_RHO", "type": "histosys"}, {"data": {"hi_data": [0.0, 0.0, 0.7211554050445557], "lo_data": [0.0, 0.0, 0.7211554050445557]}, "name": "MUON_SCALE", "type": "histosys"}, {"data": {"hi_data": [0.0, 0.0, 0.8816413879394531], "lo_data": [0.0, 0.0, 0.6520465612411499]}, "name": "SigTheoRad", "type": "histosys"}, {"data": {"hi_data": [0.0, 0.0, 0.6420041918754578], "lo_data": [0.0, 0.0, 0.6639906764030457]}, "name": "SigTheoSigQc", "type": "histosys"}, {"data": {"hi_data": [0.0, 0.0, 0.6991689801216125], "lo_data": [0.0, 0.0, 0.6683879494667053]}, "name": "SigTheoSigSc", "type": "histosys"}, {"data": {"hi": 1.04412, "lo": 0.955879}, "name": "EG_Eff", "type": "normsys"}, {"data": {"hi": 1.01774, "lo": 0.982261}, "name": "EG_Iso", "type": "normsys"}, {"data": {"hi": 1.00148, "lo": 0.998522}, "name": "EG_Reco", "type": "normsys"}, {"data": {"hi": 1.05347, "lo": 0.946535}, "name": "SigXSec", "type": "normsys"}, {"data": {"hi": 1.02387, "lo": 0.976401}, "name": "btag_BT", "type": "normsys"}, {"data": {"hi": 0.99485, "lo": 1.00515}, "name": "btag_LightT", "type": "normsys"}, {"data": {"hi": 0.973867, "lo": 0.998541}, "name": "pileup", "type": "normsys"}, {"data": {"hi": 1.76602, "lo": 0.23398}, "name": "JER_EffectiveNP_1", "type": "normsys"}, {"data": {"hi": 0.23398, "lo": 1.76602}, "name": "JER_EffectiveNP_2", "type": "normsys"}, {"data": {"hi": 1.4007, "lo": 0.599305}, "name": "JES_Flavor_Composition", "type": "normsys"}, {"data": {"hi": 1.4007, "lo": 0.599305}, "name": "JES_Pileup_OffsetMu", "type": "normsys"}, {"data": {"hi": 1.02, "lo": 0.98}, "name": "trigger", "type": "normsys"}, {"data": null, "name": "mu_SIG", "type": "normfactor"}], "name": "C1N2_Wh_hbb_250_75"}}, {"op": "add", "path": "/channels/6/samples/8", "value": {"data": [1.9971116781234741, 3.522380828857422, 3.6275386810302734], "modifiers": [{"data": null, "name": "lumi", "type": "lumi"}, {"data": [0.999754818414739, 1.396262712465355, 1.399873169658095], "name": "staterror_SRMMEM_mct2", "type": "staterror"}, {"data": {"hi_data": [1.9936375617980957, 3.510472059249878, 3.6429214477539062], "lo_data": [2.000622510910034, 3.534416913986206, 3.6119918823242188]}, "name": "EG_Eff", "type": "histosys"}, {"data": {"hi_data": [1.9969083070755005, 3.5219318866729736, 3.6281909942626953], "lo_data": [1.9973148107528687, 3.5228302478790283, 3.6268861293792725]}, "name": "EG_Iso", "type": "histosys"}, {"data": {"hi_data": [1.9972683191299438, 3.521580934524536, 3.6281819343566895], "lo_data": [1.9969545602798462, 3.523181676864624, 3.6268951892852783]}, "name": "EG_Reco", "type": "histosys"}, {"data": {"hi_data": [2.0016119480133057, 3.5291693210601807, 3.6162497997283936], "lo_data": [1.9930496215820312, 3.5163745880126953, 3.6376068592071533]}, "name": "JVT", "type": "histosys"}, {"data": {"hi_data": [1.9971116781234741, 3.522380828857422, 3.6275386810302734], "lo_data": [1.9971116781234741, 3.522380828857422, 3.6275386810302734]}, "name": "MUON_Eff_BadMuon_stat", "type": "histosys"}, {"data": {"hi_data": [1.9971116781234741, 3.522380828857422, 3.6275386810302734], "lo_data": [1.9971116781234741, 3.522380828857422, 3.6275386810302734]}, "name": "MUON_Eff_BadMuon_sys", "type": "histosys"}, {"data": {"hi_data": [1.9971213340759277, 3.522364854812622, 3.627545118331909], "lo_data": [1.9971015453338623, 3.5223965644836426, 3.627532958984375]}, "name": "MUON_Eff_Iso_stat", "type": "histosys"}, {"data": {"hi_data": [1.9968819618225098, 3.5223283767700195, 3.6278209686279297], "lo_data": [1.9973417520523071, 3.522433280944824, 3.627256155014038]}, "name": "MUON_Eff_Iso_sys", "type": "histosys"}, {"data": {"hi_data": [1.9969215393066406, 3.5221502780914307, 3.6279592514038086], "lo_data": [1.9973015785217285, 3.522611141204834, 3.6271183490753174]}, "name": "MUON_Eff_stat", "type": "histosys"}, {"data": {"hi_data": [1.9971116781234741, 3.522380828857422, 3.6275386810302734], "lo_data": [1.9971116781234741, 3.522380828857422, 3.6275386810302734]}, "name": "MUON_Eff_stat_lowpt", "type": "histosys"}, {"data": {"hi_data": [1.9967830181121826, 3.5223681926727295, 3.627880096435547], "lo_data": [1.9974409341812134, 3.5223937034606934, 3.6271965503692627]}, "name": "MUON_Eff_sys", "type": "histosys"}, {"data": {"hi_data": [1.9971116781234741, 3.522380828857422, 3.6275386810302734], "lo_data": [1.9971116781234741, 3.522380828857422, 3.6275386810302734]}, "name": "MUON_Eff_sys_lowpt", "type": "histosys"}, {"data": {"hi_data": [1.9971061944961548, 3.5222980976104736, 3.627626895904541], "lo_data": [1.9971168041229248, 3.52246356010437, 3.627450942993164]}, "name": "MUON_TTVA_stat", "type": "histosys"}, {"data": {"hi_data": [1.9971872568130493, 3.5223522186279297, 3.6274917125701904], "lo_data": [1.9970358610153198, 3.522409200668335, 3.6275861263275146]}, "name": "MUON_TTVA_sys", "type": "histosys"}, {"data": {"hi_data": [2.0072431564331055, 3.5110342502593994, 3.628753900527954], "lo_data": [1.9867645502090454, 3.5340147018432617, 3.6262521743774414]}, "name": "btag_BT", "type": "histosys"}, {"data": {"hi_data": [1.9971116781234741, 3.522380828857422, 3.6275386810302734], "lo_data": [1.9971116781234741, 3.522380828857422, 3.6275386810302734]}, "name": "btag_CT", "type": "histosys"}, {"data": {"hi_data": [1.9971116781234741, 3.522380828857422, 3.6275386810302734], "lo_data": [1.9971116781234741, 3.522380828857422, 3.6275386810302734]}, "name": "btag_Extra", "type": "histosys"}, {"data": {"hi_data": [1.9971116781234741, 3.522380828857422, 3.6275386810302734], "lo_data": [1.9971116781234741, 3.522380828857422, 3.6275386810302734]}, "name": "btag_ExtraFromCharm", "type": "histosys"}, {"data": {"hi_data": [1.9975730180740356, 3.522256851196289, 3.6272013187408447], "lo_data": [1.99665105342865, 3.5225043296813965, 3.627875804901123]}, "name": "btag_LightT", "type": "histosys"}, {"data": {"hi_data": [1.880729079246521, 3.8079066276550293, 3.458395481109619], "lo_data": [2.107466697692871, 3.2974352836608887, 3.74212908744812]}, "name": "pileup", "type": "histosys"}, {"data": {"hi_data": [1.9971116781234741, 3.522380828857422, 3.6275386810302734], "lo_data": [1.9971116781234741, 3.522380828857422, 3.6275386810302734]}, "name": "EG_RESOLUTION_ALL", "type": "histosys"}, {"data": {"hi_data": [1.9971116781234741, 3.522380828857422, 3.6275386810302734], "lo_data": [1.9971116781234741, 3.522380828857422, 3.6275386810302734]}, "name": "EG_SCALE_AF2", "type": "histosys"}, {"data": {"hi_data": [1.9971116781234741, 3.522380828857422, 3.6275386810302734], "lo_data": [1.9971116781234741, 3.522380828857422, 3.6275386810302734]}, "name": "EG_SCALE_ALL", "type": "histosys"}, {"data": {"hi_data": [1.9971116781234741, 3.522380828857422, 3.6275386810302734], "lo_data": [2.4021084308624268, 2.9131548404693604, 3.831768035888672]}, "name": "JER_DataVsMC", "type": "histosys"}, {"data": {"hi_data": [2.526968240737915, 3.4955804347991943, 3.1244826316833496], "lo_data": [1.9971116781234741, 3.522380828857422, 3.6275386810302734]}, "name": "JER_EffectiveNP_1", "type": "histosys"}, {"data": {"hi_data": [1.9971636533737183, 3.522472381591797, 3.6273951530456543], "lo_data": [1.9971116781234741, 3.522380828857422, 3.6275386810302734]}, "name": "JER_EffectiveNP_10", "type": "histosys"}, {"data": {"hi_data": [1.9971636533737183, 3.522472381591797, 3.6273951530456543], "lo_data": [1.9971116781234741, 3.522380828857422, 3.6275386810302734]}, "name": "JER_EffectiveNP_11", "type": "histosys"}, {"data": {"hi_data": [2.598487138748169, 2.9211490154266357, 3.6273951530456543], "lo_data": [1.9971116781234741, 3.522380828857422, 3.6275386810302734]}, "name": "JER_EffectiveNP_12restTerm", "type": "histosys"}, {"data": {"hi_data": [1.9971116781234741, 3.522380828857422, 3.6275386810302734], "lo_data": [2.1074976921081543, 3.7170727252960205, 3.322460889816284]}, "name": "JER_EffectiveNP_2", "type": "histosys"}, {"data": {"hi_data": [1.9971636533737183, 3.522472381591797, 3.6273951530456543], "lo_data": [2.1905415058135986, 3.103011131286621, 3.8534786701202393]}, "name": "JER_EffectiveNP_3", "type": "histosys"}, {"data": {"hi_data": [1.9971116781234741, 3.522380828857422, 3.6275386810302734], "lo_data": [1.9971636533737183, 3.522472381591797, 3.6273951530456543]}, "name": "JER_EffectiveNP_4", "type": "histosys"}, {"data": {"hi_data": [1.9971636533737183, 3.522472381591797, 3.6273951530456543], "lo_data": [1.9971116781234741, 3.522380828857422, 3.6275386810302734]}, "name": "JER_EffectiveNP_5", "type": "histosys"}, {"data": {"hi_data": [2.598419427871704, 2.9210729598999023, 3.6275386810302734], "lo_data": [1.9971636533737183, 3.522472381591797, 3.6273951530456543]}, "name": "JER_EffectiveNP_6", "type": "histosys"}, {"data": {"hi_data": [1.9971636533737183, 3.522472381591797, 3.6273951530456543], "lo_data": [1.9971116781234741, 3.522380828857422, 3.6275386810302734]}, "name": "JER_EffectiveNP_7", "type": "histosys"}, {"data": {"hi_data": [2.598419427871704, 2.9210729598999023, 3.6275386810302734], "lo_data": [1.9971636533737183, 3.522472381591797, 3.6273951530456543]}, "name": "JER_EffectiveNP_8", "type": "histosys"}, {"data": {"hi_data": [1.9971636533737183, 3.522472381591797, 3.6273951530456543], "lo_data": [1.9971116781234741, 3.522380828857422, 3.6275386810302734]}, "name": "JER_EffectiveNP_9", "type": "histosys"}, {"data": {"hi_data": [1.9971116781234741, 3.522380828857422, 3.6275386810302734], "lo_data": [1.9971116781234741, 3.522380828857422, 3.6275386810302734]}, "name": "JES_BJES_Response", "type": "histosys"}, {"data": {"hi_data": [1.9971116781234741, 3.522380828857422, 3.6275386810302734], "lo_data": [1.9971116781234741, 3.522380828857422, 3.6275386810302734]}, "name": "JES_Comb_Baseline_Kin", "type": "histosys"}, {"data": {"hi_data": [1.9971116781234741, 3.522380828857422, 3.6275386810302734], "lo_data": [1.9971116781234741, 3.522380828857422, 3.6275386810302734]}, "name": "JES_Comb_Modelling_Kin", "type": "histosys"}, {"data": {"hi_data": [1.9971116781234741, 3.522380828857422, 3.6275386810302734], "lo_data": [1.9971116781234741, 3.522380828857422, 3.6275386810302734]}, "name": "JES_Comb_TotalStat_Kin", "type": "histosys"}, {"data": {"hi_data": [1.9971116781234741, 3.522380828857422, 3.6275386810302734], "lo_data": [1.9971116781234741, 3.522380828857422, 3.6275386810302734]}, "name": "JES_Comb_Tracking_Kin", "type": "histosys"}, {"data": {"hi_data": [1.551781415939331, 3.7417709827423096, 3.8534786701202393], "lo_data": [2.598419427871704, 2.9210729598999023, 3.6275386810302734]}, "name": "JES_EffectiveNP_Detector1", "type": "histosys"}, {"data": {"hi_data": [1.9971116781234741, 3.522380828857422, 3.6275386810302734], "lo_data": [1.9971116781234741, 3.522380828857422, 3.6275386810302734]}, "name": "JES_EffectiveNP_Detector2", "type": "histosys"}, {"data": {"hi_data": [1.551781415939331, 3.7417709827423096, 3.8534786701202393], "lo_data": [2.598419427871704, 2.9210729598999023, 3.6275386810302734]}, "name": "JES_EffectiveNP_Mixed1", "type": "histosys"}, {"data": {"hi_data": [2.598419427871704, 2.9210729598999023, 3.6275386810302734], "lo_data": [1.551781415939331, 3.7417709827423096, 3.8534786701202393]}, "name": "JES_EffectiveNP_Mixed2", "type": "histosys"}, {"data": {"hi_data": [1.9971116781234741, 3.522380828857422, 3.6275386810302734], "lo_data": [1.9971116781234741, 3.522380828857422, 3.6275386810302734]}, "name": "JES_EffectiveNP_Mixed3", "type": "histosys"}, {"data": {"hi_data": [1.5518243312835693, 3.2805044651031494, 4.31470251083374], "lo_data": [2.598419427871704, 2.9210729598999023, 3.6275386810302734]}, "name": "JES_EffectiveNP_Modelling1", "type": "histosys"}, {"data": {"hi_data": [1.551781415939331, 3.7417709827423096, 3.8534786701202393], "lo_data": [2.598419427871704, 2.9210729598999023, 3.6275386810302734]}, "name": "JES_EffectiveNP_Modelling2", "type": "histosys"}, {"data": {"hi_data": [2.598419427871704, 2.9210729598999023, 3.6275386810302734], "lo_data": [1.551781415939331, 3.7417709827423096, 3.8534786701202393]}, "name": "JES_EffectiveNP_Modelling3", "type": "histosys"}, {"data": {"hi_data": [1.9971116781234741, 3.522380828857422, 3.6275386810302734], "lo_data": [2.598419427871704, 2.9210729598999023, 3.6275386810302734]}, "name": "JES_EffectiveNP_Modelling4", "type": "histosys"}, {"data": {"hi_data": [1.9971116781234741, 3.522380828857422, 3.6275386810302734], "lo_data": [2.598419427871704, 2.9210729598999023, 3.6275386810302734]}, "name": "JES_EffectiveNP_Statistical1", "type": "histosys"}, {"data": {"hi_data": [2.598419427871704, 2.9210729598999023, 3.6275386810302734], "lo_data": [1.9971116781234741, 3.522380828857422, 3.6275386810302734]}, "name": "JES_EffectiveNP_Statistical2", "type": "histosys"}, {"data": {"hi_data": [2.598419427871704, 2.9210729598999023, 3.6275386810302734], "lo_data": [1.551781415939331, 3.7417709827423096, 3.8534786701202393]}, "name": "JES_EffectiveNP_Statistical3", "type": "histosys"}, {"data": {"hi_data": [1.551781415939331, 3.7417709827423096, 3.8534786701202393], "lo_data": [2.598419427871704, 2.9210729598999023, 3.6275386810302734]}, "name": "JES_EffectiveNP_Statistical4", "type": "histosys"}, {"data": {"hi_data": [1.9971116781234741, 3.522380828857422, 3.6275386810302734], "lo_data": [1.9971116781234741, 3.522380828857422, 3.6275386810302734]}, "name": "JES_EffectiveNP_Statistical5", "type": "histosys"}, {"data": {"hi_data": [1.9971116781234741, 3.522380828857422, 3.6275386810302734], "lo_data": [2.598419427871704, 2.9210729598999023, 3.6275386810302734]}, "name": "JES_EffectiveNP_Statistical6", "type": "histosys"}, {"data": {"hi_data": [1.551781415939331, 3.7417709827423096, 3.8534786701202393], "lo_data": [2.598419427871704, 2.9210729598999023, 3.6275386810302734]}, "name": "JES_EtaIntercalibration_Modelling", "type": "histosys"}, {"data": {"hi_data": [1.9971116781234741, 3.522380828857422, 3.6275386810302734], "lo_data": [1.9971116781234741, 3.522380828857422, 3.6275386810302734]}, "name": "JES_EtaIntercalibration_NonClosure_highE", "type": "histosys"}, {"data": {"hi_data": [1.9971116781234741, 3.522380828857422, 3.6275386810302734], "lo_data": [1.9971116781234741, 3.522380828857422, 3.6275386810302734]}, "name": "JES_EtaIntercalibration_NonClosure_negEta", "type": "histosys"}, {"data": {"hi_data": [1.9971116781234741, 3.522380828857422, 3.6275386810302734], "lo_data": [1.9971116781234741, 3.522380828857422, 3.6275386810302734]}, "name": "JES_EtaIntercalibration_NonClosure_posEta", "type": "histosys"}, {"data": {"hi_data": [1.551781415939331, 3.7417709827423096, 3.8534786701202393], "lo_data": [2.598419427871704, 2.9210729598999023, 3.6275386810302734]}, "name": "JES_EtaIntercalibration_TotalStat", "type": "histosys"}, {"data": {"hi_data": [2.3111793994903564, 2.667226552963257, 4.168625354766846], "lo_data": [2.598419427871704, 2.9210729598999023, 3.6275386810302734]}, "name": "JES_Flavor_Composition", "type": "histosys"}, {"data": {"hi_data": [2.598419427871704, 2.9210729598999023, 3.6275386810302734], "lo_data": [1.645325779914856, 2.9270308017730713, 4.574674606323242]}, "name": "JES_Flavor_Response", "type": "histosys"}, {"data": {"hi_data": [1.9971116781234741, 3.522380828857422, 3.6275386810302734], "lo_data": [2.598419427871704, 2.9210729598999023, 3.6275386810302734]}, "name": "JES_Pileup_OffsetMu", "type": "histosys"}, {"data": {"hi_data": [1.5518243312835693, 3.7418744564056396, 3.853332281112671], "lo_data": [2.598419427871704, 2.9210729598999023, 3.6275386810302734]}, "name": "JES_Pileup_OffsetNPV", "type": "histosys"}, {"data": {"hi_data": [1.551781415939331, 3.7417709827423096, 3.8534786701202393], "lo_data": [2.598419427871704, 2.9210729598999023, 3.6275386810302734]}, "name": "JES_Pileup_PtTerm", "type": "histosys"}, {"data": {"hi_data": [1.5518243312835693, 3.7418744564056396, 3.853332281112671], "lo_data": [2.598419427871704, 2.9210729598999023, 3.6275386810302734]}, "name": "JES_Pileup_RhoTopology", "type": "histosys"}, {"data": {"hi_data": [1.9971116781234741, 3.522380828857422, 3.6275386810302734], "lo_data": [1.9971116781234741, 3.522380828857422, 3.6275386810302734]}, "name": "JES_SingleParticle_HighPt", "type": "histosys"}, {"data": {"hi_data": [1.9971116781234741, 3.522380828857422, 3.6275386810302734], "lo_data": [1.9971116781234741, 3.522380828857422, 3.6275386810302734]}, "name": "MET_SoftTrk", "type": "histosys"}, {"data": {"hi_data": [1.9971116781234741, 3.522380828857422, 3.6275386810302734], "lo_data": [1.9971116781234741, 3.522380828857422, 3.6275386810302734]}, "name": "MET_SoftTrk_ResoPara", "type": "histosys"}, {"data": {"hi_data": [1.9971116781234741, 3.522380828857422, 3.6275386810302734], "lo_data": [1.9971116781234741, 3.522380828857422, 3.6275386810302734]}, "name": "MET_SoftTrk_ResoPerp", "type": "histosys"}, {"data": {"hi_data": [2.350167989730835, 3.3484489917755127, 3.4484143257141113], "lo_data": [1.9971116781234741, 3.522380828857422, 3.6275386810302734]}, "name": "MUON_ID", "type": "histosys"}, {"data": {"hi_data": [1.9971116781234741, 3.522380828857422, 3.6275386810302734], "lo_data": [1.9971116781234741, 3.522380828857422, 3.6275386810302734]}, "name": "MUON_MS", "type": "histosys"}, {"data": {"hi_data": [1.9971116781234741, 3.522380828857422, 3.6275386810302734], "lo_data": [1.9971116781234741, 3.522380828857422, 3.6275386810302734]}, "name": "MUON_SAGITTA_RESBIAS", "type": "histosys"}, {"data": {"hi_data": [1.9971116781234741, 3.522380828857422, 3.6275386810302734], "lo_data": [1.9971116781234741, 3.522380828857422, 3.6275386810302734]}, "name": "MUON_SAGITTA_RHO", "type": "histosys"}, {"data": {"hi_data": [1.9971116781234741, 3.522380828857422, 3.6275386810302734], "lo_data": [1.9971116781234741, 3.522380828857422, 3.6275386810302734]}, "name": "MUON_SCALE", "type": "histosys"}, {"data": {"hi_data": [2.3916845321655273, 4.218303680419922, 4.344237804412842], "lo_data": [1.6906721591949463, 2.9819018840789795, 3.0709240436553955]}, "name": "SigTheoRad", "type": "histosys"}, {"data": {"hi_data": [1.8315479755401611, 3.230370044708252, 3.326810121536255], "lo_data": [1.8729389905929565, 3.303372621536255, 3.4019923210144043]}, "name": "SigTheoSigQc", "type": "histosys"}, {"data": {"hi_data": [2.0591981410980225, 3.631884813308716, 3.740311861038208], "lo_data": [2.0178072452545166, 3.558882236480713, 3.6651296615600586]}, "name": "SigTheoSigSc", "type": "histosys"}, {"data": {"hi": 1.00531, "lo": 0.99469}, "name": "EG_Eff", "type": "normsys"}, {"data": {"hi": 1.00024, "lo": 0.99976}, "name": "EG_Iso", "type": "normsys"}, {"data": {"hi": 1.00071, "lo": 0.999285}, "name": "EG_Reco", "type": "normsys"}, {"data": {"hi": 1.00039, "lo": 0.999389}, "name": "JVT", "type": "normsys"}, {"data": {"hi": 1.00002, "lo": 0.999979}, "name": "MUON_Eff_Iso_stat", "type": "normsys"}, {"data": {"hi": 1.0011, "lo": 0.998902}, "name": "MUON_Eff_Iso_sys", "type": "normsys"}, {"data": {"hi": 1.00029, "lo": 0.999709}, "name": "MUON_Eff_stat", "type": "normsys"}, {"data": {"hi": 1.00135, "lo": 0.998649}, "name": "MUON_Eff_sys", "type": "normsys"}, {"data": {"hi": 1.00013, "lo": 0.99987}, "name": "MUON_TTVA_stat", "type": "normsys"}, {"data": {"hi": 1.00004, "lo": 0.999964}, "name": "MUON_TTVA_sys", "type": "normsys"}, {"data": {"hi": 1.06171, "lo": 0.938294}, "name": "SigXSec", "type": "normsys"}, {"data": {"hi": 1.02465, "lo": 0.975656}, "name": "btag_BT", "type": "normsys"}, {"data": {"hi": 0.999063, "lo": 1.00094}, "name": "btag_LightT", "type": "normsys"}, {"data": {"hi": 1.02015, "lo": 0.993553}, "name": "pileup", "type": "normsys"}, {"data": {"hi": 0.939955, "lo": 1.06004}, "name": "JER_DataVsMC", "type": "normsys"}, {"data": {"hi": 1.00767, "lo": 0.992333}, "name": "JER_EffectiveNP_1", "type": "normsys"}, {"data": {"hi": 0.999974, "lo": 1.00003}, "name": "JER_EffectiveNP_10", "type": "normsys"}, {"data": {"hi": 0.999974, "lo": 1.00003}, "name": "JER_EffectiveNP_11", "type": "normsys"}, {"data": {"hi": 0.999974, "lo": 1.00003}, "name": "JER_EffectiveNP_12restTerm", "type": "normsys"}, {"data": {"hi": 1.05238, "lo": 0.947622}, "name": "JER_EffectiveNP_2", "type": "normsys"}, {"data": {"hi": 0.999974, "lo": 0.941367}, "name": "JER_EffectiveNP_3", "type": "normsys"}, {"data": {"hi": 1.00003, "lo": 0.999974}, "name": "JER_EffectiveNP_4", "type": "normsys"}, {"data": {"hi": 0.999974, "lo": 1.00003}, "name": "JER_EffectiveNP_5", "type": "normsys"}, {"data": {"hi": 1.0, "lo": 0.999974}, "name": "JER_EffectiveNP_6", "type": "normsys"}, {"data": {"hi": 0.999974, "lo": 1.00003}, "name": "JER_EffectiveNP_7", "type": "normsys"}, {"data": {"hi": 1.0, "lo": 0.999974}, "name": "JER_EffectiveNP_8", "type": "normsys"}, {"data": {"hi": 0.999974, "lo": 1.00003}, "name": "JER_EffectiveNP_9", "type": "normsys"}, {"data": {"hi": 0.941367, "lo": 1.0}, "name": "JES_EffectiveNP_Detector1", "type": "normsys"}, {"data": {"hi": 0.941367, "lo": 1.0}, "name": "JES_EffectiveNP_Mixed1", "type": "normsys"}, {"data": {"hi": 1.0, "lo": 0.941367}, "name": "JES_EffectiveNP_Mixed2", "type": "normsys"}, {"data": {"hi": 0.941341, "lo": 1.0}, "name": "JES_EffectiveNP_Modelling1", "type": "normsys"}, {"data": {"hi": 0.941367, "lo": 1.0}, "name": "JES_EffectiveNP_Modelling2", "type": "normsys"}, {"data": {"hi": 1.0, "lo": 0.941367}, "name": "JES_EffectiveNP_Modelling3", "type": "normsys"}, {"data": {"hi": 1.0, "lo": 0.941367}, "name": "JES_EffectiveNP_Statistical3", "type": "normsys"}, {"data": {"hi": 0.941367, "lo": 1.0}, "name": "JES_EffectiveNP_Statistical4", "type": "normsys"}, {"data": {"hi": 0.941367, "lo": 1.0}, "name": "JES_EtaIntercalibration_Modelling", "type": "normsys"}, {"data": {"hi": 0.941367, "lo": 1.0}, "name": "JES_EtaIntercalibration_TotalStat", "type": "normsys"}, {"data": {"hi": 0.974328, "lo": 1.0}, "name": "JES_Flavor_Composition", "type": "normsys"}, {"data": {"hi": 1.0, "lo": 0.887846}, "name": "JES_Flavor_Response", "type": "normsys"}, {"data": {"hi": 0.941341, "lo": 1.0}, "name": "JES_Pileup_OffsetNPV", "type": "normsys"}, {"data": {"hi": 0.941367, "lo": 1.0}, "name": "JES_Pileup_PtTerm", "type": "normsys"}, {"data": {"hi": 0.941341, "lo": 1.0}, "name": "JES_Pileup_RhoTopology", "type": "normsys"}, {"data": {"hi": 1.05194, "lo": 0.948056}, "name": "MUON_ID", "type": "normsys"}, {"data": {"hi": 1.02, "lo": 0.98}, "name": "trigger", "type": "normsys"}, {"data": null, "name": "mu_SIG", "type": "normfactor"}], "name": "C1N2_Wh_hbb_250_75"}}, {"op": "add", "path": "/channels/7/samples/9", "value": {"data": [8.9335298538208, 10.181699752807617, 10.036301612854004], "modifiers": [{"data": null, "name": "lumi", "type": "lumi"}, {"data": [2.2842784226306514, 2.451413198510846, 2.438508456629457], "name": "staterror_SRLMEM_mct2", "type": "staterror"}, {"data": {"hi_data": [8.918883323669434, 10.176668167114258, 10.055980682373047], "lo_data": [8.948403358459473, 10.186808586120605, 10.016318321228027]}, "name": "EG_Eff", "type": "histosys"}, {"data": {"hi_data": [8.934556007385254, 10.182758331298828, 10.03421688079834], "lo_data": [8.932502746582031, 10.180639266967773, 10.038389205932617]}, "name": "EG_Iso", "type": "histosys"}, {"data": {"hi_data": [8.933725357055664, 10.185114860534668, 10.03269100189209], "lo_data": [8.933333396911621, 10.178272247314453, 10.039925575256348]}, "name": "EG_Reco", "type": "histosys"}, {"data": {"hi_data": [8.968844413757324, 10.138569831848145, 10.044116973876953], "lo_data": [8.900510787963867, 10.220011711120605, 10.03100872039795]}, "name": "JVT", "type": "histosys"}, {"data": {"hi_data": [8.9335298538208, 10.181699752807617, 10.036301612854004], "lo_data": [8.9335298538208, 10.181699752807617, 10.036301612854004]}, "name": "MUON_Eff_BadMuon_stat", "type": "histosys"}, {"data": {"hi_data": [8.9335298538208, 10.181699752807617, 10.036301612854004], "lo_data": [8.9335298538208, 10.181699752807617, 10.036301612854004]}, "name": "MUON_Eff_BadMuon_sys", "type": "histosys"}, {"data": {"hi_data": [8.93467903137207, 10.180570602416992, 10.03628158569336], "lo_data": [8.932379722595215, 10.182828903198242, 10.036321640014648]}, "name": "MUON_Eff_Iso_stat", "type": "histosys"}, {"data": {"hi_data": [8.94223690032959, 10.17608642578125, 10.033207893371582], "lo_data": [8.924796104431152, 10.18733024597168, 10.03940486907959]}, "name": "MUON_Eff_Iso_sys", "type": "histosys"}, {"data": {"hi_data": [8.936366081237793, 10.180127143859863, 10.035037994384766], "lo_data": [8.930691719055176, 10.183273315429688, 10.037566184997559]}, "name": "MUON_Eff_stat", "type": "histosys"}, {"data": {"hi_data": [8.933289527893066, 10.17951488494873, 10.038726806640625], "lo_data": [8.933770179748535, 10.183886528015137, 10.03387451171875]}, "name": "MUON_Eff_stat_lowpt", "type": "histosys"}, {"data": {"hi_data": [8.954365730285645, 10.170804977416992, 10.026360511779785], "lo_data": [8.912601470947266, 10.192643165588379, 10.046286582946777]}, "name": "MUON_Eff_sys", "type": "histosys"}, {"data": {"hi_data": [8.935379981994629, 10.180984497070312, 10.03516674041748], "lo_data": [8.93167781829834, 10.182415008544922, 10.03743839263916]}, "name": "MUON_Eff_sys_lowpt", "type": "histosys"}, {"data": {"hi_data": [8.934128761291504, 10.181767463684082, 10.035634994506836], "lo_data": [8.932930946350098, 10.181631088256836, 10.036969184875488]}, "name": "MUON_TTVA_stat", "type": "histosys"}, {"data": {"hi_data": [8.934746742248535, 10.181351661682129, 10.035432815551758], "lo_data": [8.932312965393066, 10.182046890258789, 10.03717041015625]}, "name": "MUON_TTVA_sys", "type": "histosys"}, {"data": {"hi_data": [8.942689895629883, 10.171231269836426, 10.037610054016113], "lo_data": [8.924178123474121, 10.192636489868164, 10.034716606140137]}, "name": "btag_BT", "type": "histosys"}, {"data": {"hi_data": [8.9335298538208, 10.181699752807617, 10.036300659179688], "lo_data": [8.9335298538208, 10.181699752807617, 10.036300659179688]}, "name": "btag_CT", "type": "histosys"}, {"data": {"hi_data": [8.9335298538208, 10.181699752807617, 10.036300659179688], "lo_data": [8.9335298538208, 10.181699752807617, 10.036300659179688]}, "name": "btag_Extra", "type": "histosys"}, {"data": {"hi_data": [8.9335298538208, 10.181699752807617, 10.036300659179688], "lo_data": [8.9335298538208, 10.181699752807617, 10.036300659179688]}, "name": "btag_ExtraFromCharm", "type": "histosys"}, {"data": {"hi_data": [8.929177284240723, 10.182201385498047, 10.040152549743652], "lo_data": [8.93789005279541, 10.181191444396973, 10.032449722290039]}, "name": "btag_LightT", "type": "histosys"}, {"data": {"hi_data": [8.728832244873047, 9.930484771728516, 10.49221420288086], "lo_data": [8.94433879852295, 10.485522270202637, 9.72166919708252]}, "name": "pileup", "type": "histosys"}, {"data": {"hi_data": [8.9335298538208, 10.181699752807617, 10.036301612854004], "lo_data": [8.9335298538208, 10.181699752807617, 10.036301612854004]}, "name": "EG_RESOLUTION_ALL", "type": "histosys"}, {"data": {"hi_data": [8.9335298538208, 10.181699752807617, 10.036301612854004], "lo_data": [8.9335298538208, 10.181699752807617, 10.036301612854004]}, "name": "EG_SCALE_AF2", "type": "histosys"}, {"data": {"hi_data": [8.9335298538208, 10.181699752807617, 10.036301612854004], "lo_data": [8.9335298538208, 10.181699752807617, 10.036301612854004]}, "name": "EG_SCALE_ALL", "type": "histosys"}, {"data": {"hi_data": [8.9335298538208, 10.181699752807617, 10.036301612854004], "lo_data": [7.9478230476379395, 11.690423011779785, 9.513284683227539]}, "name": "JER_DataVsMC", "type": "histosys"}, {"data": {"hi_data": [6.3781280517578125, 12.62588119506836, 10.14752197265625], "lo_data": [8.9335298538208, 10.181699752807617, 10.036301612854004]}, "name": "JER_EffectiveNP_1", "type": "histosys"}, {"data": {"hi_data": [7.155485153198242, 12.14507007598877, 9.85097599029541], "lo_data": [8.933341979980469, 10.181794166564941, 10.036395072937012]}, "name": "JER_EffectiveNP_10", "type": "histosys"}, {"data": {"hi_data": [8.927020072937012, 10.19552230834961, 10.0289888381958], "lo_data": [7.906219959259033, 11.056965827941895, 10.188345909118652]}, "name": "JER_EffectiveNP_11", "type": "histosys"}, {"data": {"hi_data": [7.650287628173828, 11.58255386352539, 9.918689727783203], "lo_data": [8.9335298538208, 10.181699752807617, 10.036301612854004]}, "name": "JER_EffectiveNP_12restTerm", "type": "histosys"}, {"data": {"hi_data": [8.9335298538208, 10.181699752807617, 10.036301612854004], "lo_data": [6.477878093719482, 12.822826385498047, 9.850826263427734]}, "name": "JER_EffectiveNP_2", "type": "histosys"}, {"data": {"hi_data": [8.057119369506836, 10.634054183959961, 10.460357666015625], "lo_data": [8.049470901489258, 11.642139434814453, 9.459920883178711]}, "name": "JER_EffectiveNP_3", "type": "histosys"}, {"data": {"hi_data": [8.379579544067383, 10.47149658203125, 10.300455093383789], "lo_data": [7.9064202308654785, 11.434622764587402, 9.810487747192383]}, "name": "JER_EffectiveNP_4", "type": "histosys"}, {"data": {"hi_data": [7.283289432525635, 11.391806602478027, 10.476435661315918], "lo_data": [8.442198753356934, 11.109172821044922, 9.600159645080566]}, "name": "JER_EffectiveNP_5", "type": "histosys"}, {"data": {"hi_data": [8.627239227294922, 10.713711738586426, 9.810580253601074], "lo_data": [7.8693366050720215, 11.086517333984375, 10.195677757263184]}, "name": "JER_EffectiveNP_6", "type": "histosys"}, {"data": {"hi_data": [8.926833152770996, 10.195616722106934, 10.029082298278809], "lo_data": [8.627432823181152, 10.713610649108887, 9.810487747192383]}, "name": "JER_EffectiveNP_7", "type": "histosys"}, {"data": {"hi_data": [7.736644268035889, 11.814727783203125, 9.600159645080566], "lo_data": [8.927178382873535, 10.19518756866455, 10.029166221618652]}, "name": "JER_EffectiveNP_8", "type": "histosys"}, {"data": {"hi_data": [7.9064202308654785, 11.056861877441406, 10.188249588012695], "lo_data": [8.379579544067383, 10.47149658203125, 10.300455093383789]}, "name": "JER_EffectiveNP_9", "type": "histosys"}, {"data": {"hi_data": [8.9335298538208, 10.181699752807617, 10.036301612854004], "lo_data": [8.9335298538208, 10.181699752807617, 10.036301612854004]}, "name": "JES_BJES_Response", "type": "histosys"}, {"data": {"hi_data": [8.9335298538208, 10.181699752807617, 10.036301612854004], "lo_data": [8.9335298538208, 10.181699752807617, 10.036301612854004]}, "name": "JES_Comb_Baseline_Kin", "type": "histosys"}, {"data": {"hi_data": [8.9335298538208, 10.181699752807617, 10.036301612854004], "lo_data": [8.9335298538208, 10.181699752807617, 10.036301612854004]}, "name": "JES_Comb_Modelling_Kin", "type": "histosys"}, {"data": {"hi_data": [8.9335298538208, 10.181699752807617, 10.036301612854004], "lo_data": [8.9335298538208, 10.181699752807617, 10.036301612854004]}, "name": "JES_Comb_TotalStat_Kin", "type": "histosys"}, {"data": {"hi_data": [8.9335298538208, 10.181699752807617, 10.036301612854004], "lo_data": [8.9335298538208, 10.181699752807617, 10.036301612854004]}, "name": "JES_Comb_Tracking_Kin", "type": "histosys"}, {"data": {"hi_data": [8.9335298538208, 10.181699752807617, 10.036301612854004], "lo_data": [8.9335298538208, 10.181699752807617, 10.036301612854004]}, "name": "JES_EffectiveNP_Detector1", "type": "histosys"}, {"data": {"hi_data": [8.9335298538208, 10.181699752807617, 10.036301612854004], "lo_data": [8.9335298538208, 10.181699752807617, 10.036301612854004]}, "name": "JES_EffectiveNP_Detector2", "type": "histosys"}, {"data": {"hi_data": [8.9335298538208, 10.181699752807617, 10.036301612854004], "lo_data": [8.399273872375488, 10.660785675048828, 10.091471672058105]}, "name": "JES_EffectiveNP_Mixed1", "type": "histosys"}, {"data": {"hi_data": [8.627432823181152, 10.335848808288574, 10.188249588012695], "lo_data": [8.9335298538208, 10.181699752807617, 10.036301612854004]}, "name": "JES_EffectiveNP_Mixed2", "type": "histosys"}, {"data": {"hi_data": [8.9335298538208, 10.181699752807617, 10.036301612854004], "lo_data": [8.9335298538208, 10.181699752807617, 10.036301612854004]}, "name": "JES_EffectiveNP_Mixed3", "type": "histosys"}, {"data": {"hi_data": [7.640817165374756, 10.727965354919434, 10.782748222351074], "lo_data": [8.393199920654297, 11.226762771606445, 9.53156852722168]}, "name": "JES_EffectiveNP_Modelling1", "type": "histosys"}, {"data": {"hi_data": [8.933372497558594, 10.182034492492676, 10.036124229431152], "lo_data": [8.933341979980469, 10.181794166564941, 10.036395072937012]}, "name": "JES_EffectiveNP_Modelling2", "type": "histosys"}, {"data": {"hi_data": [8.9335298538208, 10.181699752807617, 10.036301612854004], "lo_data": [8.9335298538208, 10.181699752807617, 10.036301612854004]}, "name": "JES_EffectiveNP_Modelling3", "type": "histosys"}, {"data": {"hi_data": [8.9335298538208, 10.181699752807617, 10.036301612854004], "lo_data": [8.9335298538208, 10.181699752807617, 10.036301612854004]}, "name": "JES_EffectiveNP_Modelling4", "type": "histosys"}, {"data": {"hi_data": [8.9335298538208, 10.181699752807617, 10.036301612854004], "lo_data": [8.9335298538208, 10.181699752807617, 10.036301612854004]}, "name": "JES_EffectiveNP_Statistical1", "type": "histosys"}, {"data": {"hi_data": [8.933372497558594, 10.182034492492676, 10.036124229431152], "lo_data": [8.933341979980469, 10.181794166564941, 10.036395072937012]}, "name": "JES_EffectiveNP_Statistical2", "type": "histosys"}, {"data": {"hi_data": [8.9335298538208, 10.181699752807617, 10.036301612854004], "lo_data": [8.9335298538208, 10.181699752807617, 10.036301612854004]}, "name": "JES_EffectiveNP_Statistical3", "type": "histosys"}, {"data": {"hi_data": [8.9335298538208, 10.181699752807617, 10.036301612854004], "lo_data": [8.9335298538208, 10.181699752807617, 10.036301612854004]}, "name": "JES_EffectiveNP_Statistical4", "type": "histosys"}, {"data": {"hi_data": [8.9335298538208, 10.181699752807617, 10.036301612854004], "lo_data": [8.9335298538208, 10.181699752807617, 10.036301612854004]}, "name": "JES_EffectiveNP_Statistical5", "type": "histosys"}, {"data": {"hi_data": [8.9335298538208, 10.181699752807617, 10.036301612854004], "lo_data": [8.9335298538208, 10.181699752807617, 10.036301612854004]}, "name": "JES_EffectiveNP_Statistical6", "type": "histosys"}, {"data": {"hi_data": [8.51350212097168, 10.172779083251953, 10.465249061584473], "lo_data": [8.621051788330078, 10.34976577758789, 10.180713653564453]}, "name": "JES_EtaIntercalibration_Modelling", "type": "histosys"}, {"data": {"hi_data": [8.9335298538208, 10.181699752807617, 10.036301612854004], "lo_data": [8.9335298538208, 10.181699752807617, 10.036301612854004]}, "name": "JES_EtaIntercalibration_NonClosure_highE", "type": "histosys"}, {"data": {"hi_data": [8.9335298538208, 10.181699752807617, 10.036301612854004], "lo_data": [8.9335298538208, 10.181699752807617, 10.036301612854004]}, "name": "JES_EtaIntercalibration_NonClosure_negEta", "type": "histosys"}, {"data": {"hi_data": [8.9335298538208, 10.181699752807617, 10.036301612854004], "lo_data": [8.9335298538208, 10.181699752807617, 10.036301612854004]}, "name": "JES_EtaIntercalibration_NonClosure_posEta", "type": "histosys"}, {"data": {"hi_data": [8.933341979980469, 10.181794166564941, 10.036395072937012], "lo_data": [8.933372497558594, 10.182034492492676, 10.036124229431152]}, "name": "JES_EtaIntercalibration_TotalStat", "type": "histosys"}, {"data": {"hi_data": [7.715795993804932, 11.430109977722168, 10.00562572479248], "lo_data": [8.39319896697998, 12.029210090637207, 8.729121208190918]}, "name": "JES_Flavor_Composition", "type": "histosys"}, {"data": {"hi_data": [8.393199920654297, 11.226762771606445, 9.53156852722168], "lo_data": [7.209606647491455, 11.159175872802734, 10.782748222351074]}, "name": "JES_Flavor_Response", "type": "histosys"}, {"data": {"hi_data": [8.507190704345703, 10.186849594116211, 10.457490921020508], "lo_data": [8.627432823181152, 10.335848808288574, 10.188249588012695]}, "name": "JES_Pileup_OffsetMu", "type": "histosys"}, {"data": {"hi_data": [8.513833045959473, 10.172616958618164, 10.465082168579102], "lo_data": [8.748628616333008, 10.481573104858398, 9.9213285446167]}, "name": "JES_Pileup_OffsetNPV", "type": "histosys"}, {"data": {"hi_data": [8.927178382873535, 10.19518756866455, 10.029166221618652], "lo_data": [8.627432823181152, 10.335848808288574, 10.188249588012695]}, "name": "JES_Pileup_PtTerm", "type": "histosys"}, {"data": {"hi_data": [7.772886753082275, 10.913394927978516, 10.465249061584473], "lo_data": [8.39319896697998, 10.674720764160156, 10.083610534667969]}, "name": "JES_Pileup_RhoTopology", "type": "histosys"}, {"data": {"hi_data": [8.9335298538208, 10.181699752807617, 10.036301612854004], "lo_data": [8.9335298538208, 10.181699752807617, 10.036301612854004]}, "name": "JES_SingleParticle_HighPt", "type": "histosys"}, {"data": {"hi_data": [8.9335298538208, 10.181699752807617, 10.036301612854004], "lo_data": [8.627432823181152, 10.335848808288574, 10.188249588012695]}, "name": "MET_SoftTrk", "type": "histosys"}, {"data": {"hi_data": [8.787859916687012, 10.015677452087402, 10.347993850708008], "lo_data": [9.084110260009766, 10.35331916809082, 9.714101791381836]}, "name": "MET_SoftTrk_ResoPara", "type": "histosys"}, {"data": {"hi_data": [8.199393272399902, 10.860333442687988, 10.091804504394531], "lo_data": [9.671955108642578, 9.499102592468262, 9.980474472045898]}, "name": "MET_SoftTrk_ResoPerp", "type": "histosys"}, {"data": {"hi_data": [8.456049919128418, 10.178874969482422, 10.516606330871582], "lo_data": [8.787859916687012, 10.015677452087402, 10.347993850708008]}, "name": "MUON_ID", "type": "histosys"}, {"data": {"hi_data": [8.787859916687012, 10.015677452087402, 10.347993850708008], "lo_data": [8.9335298538208, 10.181699752807617, 10.036301612854004]}, "name": "MUON_MS", "type": "histosys"}, {"data": {"hi_data": [8.9335298538208, 10.181699752807617, 10.036301612854004], "lo_data": [8.713183403015137, 10.649592399597168, 9.788755416870117]}, "name": "MUON_SAGITTA_RESBIAS", "type": "histosys"}, {"data": {"hi_data": [8.9335298538208, 10.181699752807617, 10.036301612854004], "lo_data": [8.9335298538208, 10.181699752807617, 10.036301612854004]}, "name": "MUON_SAGITTA_RHO", "type": "histosys"}, {"data": {"hi_data": [8.9335298538208, 10.181699752807617, 10.036301612854004], "lo_data": [8.9335298538208, 10.181699752807617, 10.036301612854004]}, "name": "MUON_SCALE", "type": "histosys"}, {"data": {"hi_data": [10.698543548583984, 12.193316459655762, 12.01919174194336], "lo_data": [7.562756538391113, 8.619405746459961, 8.496317863464355]}, "name": "SigTheoRad", "type": "histosys"}, {"data": {"hi_data": [8.192926406860352, 9.337620735168457, 9.204277038574219], "lo_data": [8.378077507019043, 9.548640251159668, 9.412282943725586]}, "name": "SigTheoSigQc", "type": "histosys"}, {"data": {"hi_data": [9.21125602722168, 10.498229026794434, 10.348311424255371], "lo_data": [9.026104927062988, 10.287209510803223, 10.140304565429688]}, "name": "SigTheoSigSc", "type": "histosys"}, {"data": {"hi": 1.00766, "lo": 0.992335}, "name": "EG_Eff", "type": "normsys"}, {"data": {"hi": 1.00057, "lo": 0.999425}, "name": "EG_Iso", "type": "normsys"}, {"data": {"hi": 1.00182, "lo": 0.998178}, "name": "EG_Reco", "type": "normsys"}, {"data": {"hi": 1.00124, "lo": 0.998505}, "name": "JVT", "type": "normsys"}, {"data": {"hi": 1.00039, "lo": 0.999605}, "name": "MUON_Eff_Iso_stat", "type": "normsys"}, {"data": {"hi": 1.0016, "lo": 0.998404}, "name": "MUON_Eff_Iso_sys", "type": "normsys"}, {"data": {"hi": 1.00038, "lo": 0.999623}, "name": "MUON_Eff_stat", "type": "normsys"}, {"data": {"hi": 1.00031, "lo": 0.999688}, "name": "MUON_Eff_stat_lowpt", "type": "normsys"}, {"data": {"hi": 1.00224, "lo": 0.997758}, "name": "MUON_Eff_sys", "type": "normsys"}, {"data": {"hi": 1.00063, "lo": 0.99937}, "name": "MUON_Eff_sys_lowpt", "type": "normsys"}, {"data": {"hi": 1.0002, "lo": 0.999799}, "name": "MUON_TTVA_stat", "type": "normsys"}, {"data": {"hi": 1.00012, "lo": 0.999876}, "name": "MUON_TTVA_sys", "type": "normsys"}, {"data": {"hi": 1.06204, "lo": 0.937963}, "name": "SigXSec", "type": "normsys"}, {"data": {"hi": 1.02711, "lo": 0.973262}, "name": "btag_BT", "type": "normsys"}, {"data": {"hi": 0.998916, "lo": 1.00108}, "name": "btag_LightT", "type": "normsys"}, {"data": {"hi": 0.964093, "lo": 1.03462}, "name": "pileup", "type": "normsys"}, {"data": {"hi": 1.02564, "lo": 0.974355}, "name": "JER_DataVsMC", "type": "normsys"}, {"data": {"hi": 0.996355, "lo": 1.00364}, "name": "JER_EffectiveNP_1", "type": "normsys"}, {"data": {"hi": 0.981037, "lo": 0.999991}, "name": "JER_EffectiveNP_10", "type": "normsys"}, {"data": {"hi": 1.00073, "lo": 0.985077}, "name": "JER_EffectiveNP_11", "type": "normsys"}, {"data": {"hi": 0.97434, "lo": 1.02566}, "name": "JER_EffectiveNP_12restTerm", "type": "normsys"}, {"data": {"hi": 1.01895, "lo": 0.981052}, "name": "JER_EffectiveNP_2", "type": "normsys"}, {"data": {"hi": 0.959461, "lo": 1.02159}, "name": "JER_EffectiveNP_3", "type": "normsys"}, {"data": {"hi": 0.974355, "lo": 0.985086}, "name": "JER_EffectiveNP_4", "type": "normsys"}, {"data": {"hi": 0.957988, "lo": 1.00667}, "name": "JER_EffectiveNP_5", "type": "normsys"}, {"data": {"hi": 0.985077, "lo": 0.984368}, "name": "JER_EffectiveNP_6", "type": "normsys"}, {"data": {"hi": 1.00072, "lo": 0.985086}, "name": "JER_EffectiveNP_7", "type": "normsys"}, {"data": {"hi": 1.00667, "lo": 1.00071}, "name": "JER_EffectiveNP_8", "type": "normsys"}, {"data": {"hi": 0.985086, "lo": 0.974355}, "name": "JER_EffectiveNP_9", "type": "normsys"}, {"data": {"hi": 1.04494, "lo": 0.955061}, "name": "JES_EffectiveNP_Mixed1", "type": "normsys"}, {"data": {"hi": 0.985086, "lo": 1.01491}, "name": "JES_EffectiveNP_Mixed2", "type": "normsys"}, {"data": {"hi": 0.975588, "lo": 0.955805}, "name": "JES_EffectiveNP_Modelling1", "type": "normsys"}, {"data": {"hi": 1.00002, "lo": 0.999991}, "name": "JES_EffectiveNP_Modelling2", "type": "normsys"}, {"data": {"hi": 1.00002, "lo": 0.999991}, "name": "JES_EffectiveNP_Statistical2", "type": "normsys"}, {"data": {"hi": 0.959012, "lo": 0.985815}, "name": "JES_EtaIntercalibration_Modelling", "type": "normsys"}, {"data": {"hi": 0.999991, "lo": 1.00002}, "name": "JES_EtaIntercalibration_TotalStat", "type": "normsys"}, {"data": {"hi": 0.998626, "lo": 0.955805}, "name": "JES_Flavor_Composition", "type": "normsys"}, {"data": {"hi": 0.955805, "lo": 0.975588}, "name": "JES_Flavor_Response", "type": "normsys"}, {"data": {"hi": 0.959724, "lo": 0.985086}, "name": "JES_Pileup_OffsetMu", "type": "normsys"}, {"data": {"hi": 0.959028, "lo": 0.971439}, "name": "JES_Pileup_OffsetNPV", "type": "normsys"}, {"data": {"hi": 1.00071, "lo": 0.985086}, "name": "JES_Pileup_PtTerm", "type": "normsys"}, {"data": {"hi": 0.959012, "lo": 0.955805}, "name": "JES_Pileup_RhoTopology", "type": "normsys"}, {"data": {"hi": 1.01491, "lo": 0.985086}, "name": "MET_SoftTrk", "type": "normsys"}, {"data": {"hi": 1.01658, "lo": 0.983424}, "name": "MET_SoftTrk_ResoPara", "type": "normsys"}, {"data": {"hi": 1.00291, "lo": 0.997088}, "name": "MET_SoftTrk_ResoPerp", "type": "normsys"}, {"data": {"hi": 1.00028, "lo": 1.01658}, "name": "MUON_ID", "type": "normsys"}, {"data": {"hi": 1.01658, "lo": 0.983424}, "name": "MUON_MS", "type": "normsys"}, {"data": {"hi": 0.974711, "lo": 1.02529}, "name": "MUON_SAGITTA_RESBIAS", "type": "normsys"}, {"data": {"hi": 1.02, "lo": 0.98}, "name": "trigger", "type": "normsys"}, {"data": null, "name": "mu_SIG", "type": "normfactor"}], "name": "C1N2_Wh_hbb_250_75"}}]
